{
  "generated_at": "2026-07-02",
  "source_url": "https://forum.gamer.com.tw/",
  "category": {
    "slug": "mobile",
    "label": "手機遊戲哈啦區",
    "board_count": 120
  },
  "boards": [
    {
      "rank": 1,
      "title": "原神",
      "popularity": 204526,
      "article": 265,
      "bsn": 36730,
      "board_url": "https://forum.gamer.com.tw/B.php?bsn=36730",
      "category_slug": "mobile",
      "category_label": "手機遊戲哈啦區"
    },
    {
      "rank": 2,
      "title": "SD 鋼彈 G 世代 永恆",
      "popularity": 160471,
      "article": 81,
      "bsn": 74906,
      "board_url": "https://forum.gamer.com.tw/B.php?bsn=74906",
      "category_slug": "mobile",
      "category_label": "手機遊戲哈啦區"
    },
    {
      "rank": 3,
      "title": "鳴潮",
      "popularity": 151404,
      "article": 59,
      "bsn": 74934,
      "board_url": "https://forum.gamer.com.tw/B.php?bsn=74934",
      "category_slug": "mobile",
      "category_label": "手機遊戲哈啦區"
    },
    {
      "rank": 4,
      "title": "棕色塵埃 2",
      "popularity": 146162,
      "article": 43,
      "bsn": 76207,
      "board_url": "https://forum.gamer.com.tw/B.php?bsn=76207",
      "category_slug": "mobile",
      "category_label": "手機遊戲哈啦區"
    },
    {
      "rank": 5,
      "title": "勝利女神：妮姬",
      "popularity": 129340,
      "article": 56,
      "bsn": 36390,
      "board_url": "https://forum.gamer.com.tw/B.php?bsn=36390",
      "category_slug": "mobile",
      "category_label": "手機遊戲哈啦區"
    },
    {
      "rank": 6,
      "title": "異環",
      "popularity": 127209,
      "article": 81,
      "bsn": 80679,
      "board_url": "https://forum.gamer.com.tw/B.php?bsn=80679",
      "category_slug": "mobile",
      "category_label": "手機遊戲哈啦區"
    },
    {
      "rank": 7,
      "title": "Fate/Grand Order",
      "popularity": 111434,
      "article": 62,
      "bsn": 26742,
      "board_url": "https://forum.gamer.com.tw/B.php?bsn=26742",
      "category_slug": "mobile",
      "category_label": "手機遊戲哈啦區"
    },
    {
      "rank": 8,
      "title": "神魔之塔",
      "popularity": 95043,
      "article": 143,
      "bsn": 23805,
      "board_url": "https://forum.gamer.com.tw/B.php?bsn=23805",
      "category_slug": "mobile",
      "category_label": "手機遊戲哈啦區"
    },
    {
      "rank": 9,
      "title": "貓咪大戰爭（にゃんこ大戦争）",
      "popularity": 86930,
      "article": 8,
      "bsn": 23772,
      "board_url": "https://forum.gamer.com.tw/B.php?bsn=23772",
      "category_slug": "mobile",
      "category_label": "手機遊戲哈啦區"
    },
    {
      "rank": 10,
      "title": "崩壞：星穹鐵道",
      "popularity": 72387,
      "article": 46,
      "bsn": 72822,
      "board_url": "https://forum.gamer.com.tw/B.php?bsn=72822",
      "category_slug": "mobile",
      "category_label": "手機遊戲哈啦區"
    },
    {
      "rank": 11,
      "title": "天堂 Mobile",
      "popularity": 57139,
      "article": 31,
      "bsn": 25908,
      "board_url": "https://forum.gamer.com.tw/B.php?bsn=25908",
      "category_slug": "mobile",
      "category_label": "手機遊戲哈啦區"
    },
    {
      "rank": 12,
      "title": "闇影詩章 Shadowverse",
      "popularity": 56375,
      "article": 80,
      "bsn": 29330,
      "board_url": "https://forum.gamer.com.tw/B.php?bsn=29330",
      "category_slug": "mobile",
      "category_label": "手機遊戲哈啦區"
    },
    {
      "rank": 13,
      "title": "瑞利昂 (RELLION)：NPC 的生存記",
      "popularity": 46728,
      "article": 10,
      "bsn": 85516,
      "board_url": "https://forum.gamer.com.tw/B.php?bsn=85516",
      "category_slug": "mobile",
      "category_label": "手機遊戲哈啦區"
    },
    {
      "rank": 14,
      "title": "絕區零",
      "popularity": 39477,
      "article": 27,
      "bsn": 74860,
      "board_url": "https://forum.gamer.com.tw/B.php?bsn=74860",
      "category_slug": "mobile",
      "category_label": "手機遊戲哈啦區"
    },
    {
      "rank": 15,
      "title": "超異域公主連結☆Re:Dive",
      "popularity": 39395,
      "article": 94,
      "bsn": 30861,
      "board_url": "https://forum.gamer.com.tw/B.php?bsn=30861",
      "category_slug": "mobile",
      "category_label": "手機遊戲哈啦區"
    },
    {
      "rank": 16,
      "title": "星絆之旅",
      "popularity": 39003,
      "article": 15,
      "bsn": 83743,
      "board_url": "https://forum.gamer.com.tw/B.php?bsn=83743",
      "category_slug": "mobile",
      "category_label": "手機遊戲哈啦區"
    },
    {
      "rank": 17,
      "title": "賽馬娘Pretty Derby",
      "popularity": 38312,
      "article": 100,
      "bsn": 34421,
      "board_url": "https://forum.gamer.com.tw/B.php?bsn=34421",
      "category_slug": "mobile",
      "category_label": "手機遊戲哈啦區"
    },
    {
      "rank": 18,
      "title": "蔚藍檔案",
      "popularity": 37775,
      "article": 21,
      "bsn": 38898,
      "board_url": "https://forum.gamer.com.tw/B.php?bsn=38898",
      "category_slug": "mobile",
      "category_label": "手機遊戲哈啦區"
    },
    {
      "rank": 19,
      "title": "RO 仙境傳說：世界之旅",
      "popularity": 37439,
      "article": 10,
      "bsn": 83054,
      "board_url": "https://forum.gamer.com.tw/B.php?bsn=83054",
      "category_slug": "mobile",
      "category_label": "手機遊戲哈啦區"
    },
    {
      "rank": 20,
      "title": "怪物彈珠",
      "popularity": 33856,
      "article": 107,
      "bsn": 25052,
      "board_url": "https://forum.gamer.com.tw/B.php?bsn=25052",
      "category_slug": "mobile",
      "category_label": "手機遊戲哈啦區"
    },
    {
      "rank": 21,
      "title": "天堂 W",
      "popularity": 31672,
      "article": 9,
      "bsn": 71905,
      "board_url": "https://forum.gamer.com.tw/B.php?bsn=71905",
      "category_slug": "mobile",
      "category_label": "手機遊戲哈啦區"
    },
    {
      "rank": 22,
      "title": "明日方舟：終末地",
      "popularity": 31182,
      "article": 29,
      "bsn": 74604,
      "board_url": "https://forum.gamer.com.tw/B.php?bsn=74604",
      "category_slug": "mobile",
      "category_label": "手機遊戲哈啦區"
    },
    {
      "rank": 23,
      "title": "Pokemon GO",
      "popularity": 25773,
      "article": 12,
      "bsn": 29659,
      "board_url": "https://forum.gamer.com.tw/B.php?bsn=29659",
      "category_slug": "mobile",
      "category_label": "手機遊戲哈啦區"
    },
    {
      "rank": 24,
      "title": "辟邪除妖 Variants Daphne",
      "popularity": 24491,
      "article": 8,
      "bsn": 70180,
      "board_url": "https://forum.gamer.com.tw/B.php?bsn=70180",
      "category_slug": "mobile",
      "category_label": "手機遊戲哈啦區"
    },
    {
      "rank": 25,
      "title": "龍村 3",
      "popularity": 24185,
      "article": 16,
      "bsn": 85385,
      "board_url": "https://forum.gamer.com.tw/B.php?bsn=85385",
      "category_slug": "mobile",
      "category_label": "手機遊戲哈啦區"
    },
    {
      "rank": 26,
      "title": "明日方舟",
      "popularity": 23982,
      "article": 11,
      "bsn": 33651,
      "board_url": "https://forum.gamer.com.tw/B.php?bsn=33651",
      "category_slug": "mobile",
      "category_label": "手機遊戲哈啦區"
    },
    {
      "rank": 27,
      "title": "卡厄思夢境",
      "popularity": 22532,
      "article": 15,
      "bsn": 80099,
      "board_url": "https://forum.gamer.com.tw/B.php?bsn=80099",
      "category_slug": "mobile",
      "category_label": "手機遊戲哈啦區"
    },
    {
      "rank": 28,
      "title": "傳說對決 Arena of Valor",
      "popularity": 21874,
      "article": 28,
      "bsn": 30518,
      "board_url": "https://forum.gamer.com.tw/B.php?bsn=30518",
      "category_slug": "mobile",
      "category_label": "手機遊戲哈啦區"
    },
    {
      "rank": 29,
      "title": "Pikmin Bloom",
      "popularity": 19880,
      "article": 13,
      "bsn": 72889,
      "board_url": "https://forum.gamer.com.tw/B.php?bsn=72889",
      "category_slug": "mobile",
      "category_label": "手機遊戲哈啦區"
    },
    {
      "rank": 30,
      "title": "第七史詩",
      "popularity": 18503,
      "article": 15,
      "bsn": 34880,
      "board_url": "https://forum.gamer.com.tw/B.php?bsn=34880",
      "category_slug": "mobile",
      "category_label": "手機遊戲哈啦區"
    },
    {
      "rank": 31,
      "title": "少女前線 2：追放",
      "popularity": 17983,
      "article": 55,
      "bsn": 70502,
      "board_url": "https://forum.gamer.com.tw/B.php?bsn=70502",
      "category_slug": "mobile",
      "category_label": "手機遊戲哈啦區"
    },
    {
      "rank": 32,
      "title": "XXL 猛漢町",
      "popularity": 17651,
      "article": 6,
      "bsn": 80107,
      "board_url": "https://forum.gamer.com.tw/B.php?bsn=80107",
      "category_slug": "mobile",
      "category_label": "手機遊戲哈啦區"
    },
    {
      "rank": 33,
      "title": "寶可夢集換式卡牌遊戲口袋版",
      "popularity": 17395,
      "article": 41,
      "bsn": 79688,
      "board_url": "https://forum.gamer.com.tw/B.php?bsn=79688",
      "category_slug": "mobile",
      "category_label": "手機遊戲哈啦區"
    },
    {
      "rank": 34,
      "title": "JUMP 全明星亂鬥",
      "popularity": 17150,
      "article": 23,
      "bsn": 84902,
      "board_url": "https://forum.gamer.com.tw/B.php?bsn=84902",
      "category_slug": "mobile",
      "category_label": "手機遊戲哈啦區"
    },
    {
      "rank": 35,
      "title": "Monster Hunter Now",
      "popularity": 15908,
      "article": 7,
      "bsn": 77414,
      "board_url": "https://forum.gamer.com.tw/B.php?bsn=77414",
      "category_slug": "mobile",
      "category_label": "手機遊戲哈啦區"
    },
    {
      "rank": 36,
      "title": "碧藍幻想 系列",
      "popularity": 15438,
      "article": 30,
      "bsn": 25204,
      "board_url": "https://forum.gamer.com.tw/B.php?bsn=25204",
      "category_slug": "mobile",
      "category_label": "手機遊戲哈啦區"
    },
    {
      "rank": 37,
      "title": "三國志•戰略版",
      "popularity": 13949,
      "article": 3,
      "bsn": 36815,
      "board_url": "https://forum.gamer.com.tw/B.php?bsn=36815",
      "category_slug": "mobile",
      "category_label": "手機遊戲哈啦區"
    },
    {
      "rank": 38,
      "title": "勇者鬥惡龍 破限亂鬥",
      "popularity": 13302,
      "article": 21,
      "bsn": 83661,
      "board_url": "https://forum.gamer.com.tw/B.php?bsn=83661",
      "category_slug": "mobile",
      "category_label": "手機遊戲哈啦區"
    },
    {
      "rank": 39,
      "title": "星塔旅人",
      "popularity": 12795,
      "article": 13,
      "bsn": 81566,
      "board_url": "https://forum.gamer.com.tw/B.php?bsn=81566",
      "category_slug": "mobile",
      "category_label": "手機遊戲哈啦區"
    },
    {
      "rank": 40,
      "title": "天地劫 手機版",
      "popularity": 12092,
      "article": 5,
      "bsn": 38462,
      "board_url": "https://forum.gamer.com.tw/B.php?bsn=38462",
      "category_slug": "mobile",
      "category_label": "手機遊戲哈啦區"
    },
    {
      "rank": 41,
      "title": "瑪奇 Mobile",
      "popularity": 11416,
      "article": 14,
      "bsn": 32564,
      "board_url": "https://forum.gamer.com.tw/B.php?bsn=32564",
      "category_slug": "mobile",
      "category_label": "手機遊戲哈啦區"
    },
    {
      "rank": 42,
      "title": "星之救援者 StarSavior",
      "popularity": 11061,
      "article": 6,
      "bsn": 81995,
      "board_url": "https://forum.gamer.com.tw/B.php?bsn=81995",
      "category_slug": "mobile",
      "category_label": "手機遊戲哈啦區"
    },
    {
      "rank": 43,
      "title": "煙雨江湖",
      "popularity": 10561,
      "article": 5,
      "bsn": 71402,
      "board_url": "https://forum.gamer.com.tw/B.php?bsn=71402",
      "category_slug": "mobile",
      "category_label": "手機遊戲哈啦區"
    },
    {
      "rank": 44,
      "title": "楓之谷 M",
      "popularity": 10463,
      "article": 0,
      "bsn": 29461,
      "board_url": "https://forum.gamer.com.tw/B.php?bsn=29461",
      "category_slug": "mobile",
      "category_label": "手機遊戲哈啦區"
    },
    {
      "rank": 45,
      "title": "碧藍航線",
      "popularity": 9947,
      "article": 1,
      "bsn": 32550,
      "board_url": "https://forum.gamer.com.tw/B.php?bsn=32550",
      "category_slug": "mobile",
      "category_label": "手機遊戲哈啦區"
    },
    {
      "rank": 46,
      "title": "嘟嘟臉惡作劇",
      "popularity": 9070,
      "article": 5,
      "bsn": 78781,
      "board_url": "https://forum.gamer.com.tw/B.php?bsn=78781",
      "category_slug": "mobile",
      "category_label": "手機遊戲哈啦區"
    },
    {
      "rank": 47,
      "title": "RO 仙境傳說 3",
      "popularity": 7950,
      "article": 5,
      "bsn": 81475,
      "board_url": "https://forum.gamer.com.tw/B.php?bsn=81475",
      "category_slug": "mobile",
      "category_label": "手機遊戲哈啦區"
    },
    {
      "rank": 48,
      "title": "魔靈召喚",
      "popularity": 7734,
      "article": 7,
      "bsn": 26380,
      "board_url": "https://forum.gamer.com.tw/B.php?bsn=26380",
      "category_slug": "mobile",
      "category_label": "手機遊戲哈啦區"
    },
    {
      "rank": 49,
      "title": "Another Eden：穿越時空的貓",
      "popularity": 7652,
      "article": 2,
      "bsn": 29220,
      "board_url": "https://forum.gamer.com.tw/B.php?bsn=29220",
      "category_slug": "mobile",
      "category_label": "手機遊戲哈啦區"
    },
    {
      "rank": 50,
      "title": "雙面神姬",
      "popularity": 7568,
      "article": 28,
      "bsn": 85535,
      "board_url": "https://forum.gamer.com.tw/B.php?bsn=85535",
      "category_slug": "mobile",
      "category_label": "手機遊戲哈啦區"
    },
    {
      "rank": 51,
      "title": "楓之谷：放置冒險記",
      "popularity": 7003,
      "article": 0,
      "bsn": 82899,
      "board_url": "https://forum.gamer.com.tw/B.php?bsn=82899",
      "category_slug": "mobile",
      "category_label": "手機遊戲哈啦區"
    },
    {
      "rank": 52,
      "title": "心動小鎮",
      "popularity": 6830,
      "article": 4,
      "bsn": 75403,
      "board_url": "https://forum.gamer.com.tw/B.php?bsn=75403",
      "category_slug": "mobile",
      "category_label": "手機遊戲哈啦區"
    },
    {
      "rank": 53,
      "title": "荒野亂鬥",
      "popularity": 6577,
      "article": 4,
      "bsn": 32407,
      "board_url": "https://forum.gamer.com.tw/B.php?bsn=32407",
      "category_slug": "mobile",
      "category_label": "手機遊戲哈啦區"
    },
    {
      "rank": 54,
      "title": "RO 新世代：攜手同行",
      "popularity": 6376,
      "article": 4,
      "bsn": 37030,
      "board_url": "https://forum.gamer.com.tw/B.php?bsn=37030",
      "category_slug": "mobile",
      "category_label": "手機遊戲哈啦區"
    },
    {
      "rank": 55,
      "title": "Limbus Company",
      "popularity": 6208,
      "article": 7,
      "bsn": 73052,
      "board_url": "https://forum.gamer.com.tw/B.php?bsn=73052",
      "category_slug": "mobile",
      "category_label": "手機遊戲哈啦區"
    },
    {
      "rank": 56,
      "title": "信長之野望 真戰",
      "popularity": 6017,
      "article": 6,
      "bsn": 82869,
      "board_url": "https://forum.gamer.com.tw/B.php?bsn=82869",
      "category_slug": "mobile",
      "category_label": "手機遊戲哈啦區"
    },
    {
      "rank": 57,
      "title": "寒霜啟示錄",
      "popularity": 5979,
      "article": 8,
      "bsn": 76999,
      "board_url": "https://forum.gamer.com.tw/B.php?bsn=76999",
      "category_slug": "mobile",
      "category_label": "手機遊戲哈啦區"
    },
    {
      "rank": 58,
      "title": "女神異聞錄：夜幕魅影",
      "popularity": 5930,
      "article": 19,
      "bsn": 71034,
      "board_url": "https://forum.gamer.com.tw/B.php?bsn=71034",
      "category_slug": "mobile",
      "category_label": "手機遊戲哈啦區"
    },
    {
      "rank": 59,
      "title": "運氣拼輸贏",
      "popularity": 5753,
      "article": 0,
      "bsn": 80385,
      "board_url": "https://forum.gamer.com.tw/B.php?bsn=80385",
      "category_slug": "mobile",
      "category_label": "手機遊戲哈啦區"
    },
    {
      "rank": 60,
      "title": "杖劍傳說：坎斯汀之約",
      "popularity": 5723,
      "article": 0,
      "bsn": 80389,
      "board_url": "https://forum.gamer.com.tw/B.php?bsn=80389",
      "category_slug": "mobile",
      "category_label": "手機遊戲哈啦區"
    },
    {
      "rank": 61,
      "title": "像素深淵",
      "popularity": 5686,
      "article": 5,
      "bsn": 85250,
      "board_url": "https://forum.gamer.com.tw/B.php?bsn=85250",
      "category_slug": "mobile",
      "category_label": "手機遊戲哈啦區"
    },
    {
      "rank": 62,
      "title": "Crash Fever",
      "popularity": 5675,
      "article": 6,
      "bsn": 28611,
      "board_url": "https://forum.gamer.com.tw/B.php?bsn=28611",
      "category_slug": "mobile",
      "category_label": "手機遊戲哈啦區"
    },
    {
      "rank": 63,
      "title": "忘卻前夜 Morimens",
      "popularity": 5656,
      "article": 6,
      "bsn": 78829,
      "board_url": "https://forum.gamer.com.tw/B.php?bsn=78829",
      "category_slug": "mobile",
      "category_label": "手機遊戲哈啦區"
    },
    {
      "rank": 64,
      "title": "Rogue with the Dead - 亡途轉生",
      "popularity": 5406,
      "article": 1,
      "bsn": 81808,
      "board_url": "https://forum.gamer.com.tw/B.php?bsn=81808",
      "category_slug": "mobile",
      "category_label": "手機遊戲哈啦區"
    },
    {
      "rank": 65,
      "title": "緋染天空 Heaven Burns Red",
      "popularity": 5384,
      "article": 3,
      "bsn": 37697,
      "board_url": "https://forum.gamer.com.tw/B.php?bsn=37697",
      "category_slug": "mobile",
      "category_label": "手機遊戲哈啦區"
    },
    {
      "rank": 66,
      "title": "Pokémon Sleep",
      "popularity": 5332,
      "article": 25,
      "bsn": 36685,
      "board_url": "https://forum.gamer.com.tw/B.php?bsn=36685",
      "category_slug": "mobile",
      "category_label": "手機遊戲哈啦區"
    },
    {
      "rank": 67,
      "title": "世界計畫 繽紛舞台！ feat. 初音未來",
      "popularity": 5232,
      "article": 1,
      "bsn": 37505,
      "board_url": "https://forum.gamer.com.tw/B.php?bsn=37505",
      "category_slug": "mobile",
      "category_label": "手機遊戲哈啦區"
    },
    {
      "rank": 68,
      "title": "鈴蘭之劍：爲這和平的世界",
      "popularity": 5147,
      "article": 2,
      "bsn": 71838,
      "board_url": "https://forum.gamer.com.tw/B.php?bsn=71838",
      "category_slug": "mobile",
      "category_label": "手機遊戲哈啦區"
    },
    {
      "rank": 69,
      "title": "重返未來：1999",
      "popularity": 5116,
      "article": 2,
      "bsn": 75028,
      "board_url": "https://forum.gamer.com.tw/B.php?bsn=75028",
      "category_slug": "mobile",
      "category_label": "手機遊戲哈啦區"
    },
    {
      "rank": 70,
      "title": "白貓 Project",
      "popularity": 5116,
      "article": 6,
      "bsn": 26686,
      "board_url": "https://forum.gamer.com.tw/B.php?bsn=26686",
      "category_slug": "mobile",
      "category_label": "手機遊戲哈啦區"
    },
    {
      "rank": 71,
      "title": "七騎士 RE:BIRTH",
      "popularity": 5088,
      "article": 1,
      "bsn": 79741,
      "board_url": "https://forum.gamer.com.tw/B.php?bsn=79741",
      "category_slug": "mobile",
      "category_label": "手機遊戲哈啦區"
    },
    {
      "rank": 72,
      "title": "交錯戰線",
      "popularity": 5025,
      "article": 7,
      "bsn": 79104,
      "board_url": "https://forum.gamer.com.tw/B.php?bsn=79104",
      "category_slug": "mobile",
      "category_label": "手機遊戲哈啦區"
    },
    {
      "rank": 73,
      "title": "夢幻模擬戰 手機版",
      "popularity": 5022,
      "article": 0,
      "bsn": 33596,
      "board_url": "https://forum.gamer.com.tw/B.php?bsn=33596",
      "category_slug": "mobile",
      "category_label": "手機遊戲哈啦區"
    },
    {
      "rank": 74,
      "title": "MLB：9 局職棒 系列",
      "popularity": 4855,
      "article": 2,
      "bsn": 31114,
      "board_url": "https://forum.gamer.com.tw/B.php?bsn=31114",
      "category_slug": "mobile",
      "category_label": "手機遊戲哈啦區"
    },
    {
      "rank": 75,
      "title": "LINE Rangers 銀河特攻隊",
      "popularity": 4828,
      "article": 3,
      "bsn": 25967,
      "board_url": "https://forum.gamer.com.tw/B.php?bsn=25967",
      "category_slug": "mobile",
      "category_label": "手機遊戲哈啦區"
    },
    {
      "rank": 76,
      "title": "最後的克勞迪亞",
      "popularity": 4749,
      "article": 1,
      "bsn": 35735,
      "board_url": "https://forum.gamer.com.tw/B.php?bsn=35735",
      "category_slug": "mobile",
      "category_label": "手機遊戲哈啦區"
    },
    {
      "rank": 77,
      "title": "戀與深空",
      "popularity": 4730,
      "article": 7,
      "bsn": 39445,
      "board_url": "https://forum.gamer.com.tw/B.php?bsn=39445",
      "category_slug": "mobile",
      "category_label": "手機遊戲哈啦區"
    },
    {
      "rank": 78,
      "title": "龍族拼圖 Puzzle & Dragons",
      "popularity": 4656,
      "article": 2,
      "bsn": 22153,
      "board_url": "https://forum.gamer.com.tw/B.php?bsn=22153",
      "category_slug": "mobile",
      "category_label": "手機遊戲哈啦區"
    },
    {
      "rank": 79,
      "title": "DRAGON BALL Z -七龍珠爆裂激戰-",
      "popularity": 4594,
      "article": 1,
      "bsn": 27096,
      "board_url": "https://forum.gamer.com.tw/B.php?bsn=27096",
      "category_slug": "mobile",
      "category_label": "手機遊戲哈啦區"
    },
    {
      "rank": 80,
      "title": "Bleach：刀鳴",
      "popularity": 4497,
      "article": 13,
      "bsn": 78017,
      "board_url": "https://forum.gamer.com.tw/B.php?bsn=78017",
      "category_slug": "mobile",
      "category_label": "手機遊戲哈啦區"
    },
    {
      "rank": 81,
      "title": "Kingshot",
      "popularity": 4347,
      "article": 1,
      "bsn": 82382,
      "board_url": "https://forum.gamer.com.tw/B.php?bsn=82382",
      "category_slug": "mobile",
      "category_label": "手機遊戲哈啦區"
    },
    {
      "rank": 82,
      "title": "英雄傳說 卡卡布三部曲",
      "popularity": 4312,
      "article": 1,
      "bsn": 80736,
      "board_url": "https://forum.gamer.com.tw/B.php?bsn=80736",
      "category_slug": "mobile",
      "category_label": "手機遊戲哈啦區"
    },
    {
      "rank": 83,
      "title": "寶可夢大師",
      "popularity": 4291,
      "article": 2,
      "bsn": 36673,
      "board_url": "https://forum.gamer.com.tw/B.php?bsn=36673",
      "category_slug": "mobile",
      "category_label": "手機遊戲哈啦區"
    },
    {
      "rank": 84,
      "title": "生存 33 天",
      "popularity": 4290,
      "article": 2,
      "bsn": 85588,
      "board_url": "https://forum.gamer.com.tw/B.php?bsn=85588",
      "category_slug": "mobile",
      "category_label": "手機遊戲哈啦區"
    },
    {
      "rank": 85,
      "title": "召喚圖板 Summons Board",
      "popularity": 3779,
      "article": 3,
      "bsn": 25691,
      "board_url": "https://forum.gamer.com.tw/B.php?bsn=25691",
      "category_slug": "mobile",
      "category_label": "手機遊戲哈啦區"
    },
    {
      "rank": 86,
      "title": "逆水寒",
      "popularity": 3753,
      "article": 0,
      "bsn": 77001,
      "board_url": "https://forum.gamer.com.tw/B.php?bsn=77001",
      "category_slug": "mobile",
      "category_label": "手機遊戲哈啦區"
    },
    {
      "rank": 87,
      "title": "魔法少女小圓 Magia Exedra（原：魔法紀錄）",
      "popularity": 3644,
      "article": 8,
      "bsn": 31057,
      "board_url": "https://forum.gamer.com.tw/B.php?bsn=31057",
      "category_slug": "mobile",
      "category_label": "手機遊戲哈啦區"
    },
    {
      "rank": 88,
      "title": "部落衝突：皇室戰爭",
      "popularity": 3619,
      "article": 5,
      "bsn": 29712,
      "board_url": "https://forum.gamer.com.tw/B.php?bsn=29712",
      "category_slug": "mobile",
      "category_label": "手機遊戲哈啦區"
    },
    {
      "rank": 89,
      "title": "我想成為影之強者！Master of Garden",
      "popularity": 3568,
      "article": 3,
      "bsn": 75993,
      "board_url": "https://forum.gamer.com.tw/B.php?bsn=75993",
      "category_slug": "mobile",
      "category_label": "手機遊戲哈啦區"
    },
    {
      "rank": 90,
      "title": "二重螺旋",
      "popularity": 3480,
      "article": 5,
      "bsn": 78855,
      "board_url": "https://forum.gamer.com.tw/B.php?bsn=78855",
      "category_slug": "mobile",
      "category_label": "手機遊戲哈啦區"
    },
    {
      "rank": 91,
      "title": "點點英雄：骰子傳說",
      "popularity": 3363,
      "article": 2,
      "bsn": 85135,
      "board_url": "https://forum.gamer.com.tw/B.php?bsn=85135",
      "category_slug": "mobile",
      "category_label": "手機遊戲哈啦區"
    },
    {
      "rank": 92,
      "title": "MLB 勁旅對決",
      "popularity": 3344,
      "article": 2,
      "bsn": 77583,
      "board_url": "https://forum.gamer.com.tw/B.php?bsn=77583",
      "category_slug": "mobile",
      "category_label": "手機遊戲哈啦區"
    },
    {
      "rank": 93,
      "title": "緋紅的神約 Echocalypse",
      "popularity": 3300,
      "article": 2,
      "bsn": 75058,
      "board_url": "https://forum.gamer.com.tw/B.php?bsn=75058",
      "category_slug": "mobile",
      "category_label": "手機遊戲哈啦區"
    },
    {
      "rank": 94,
      "title": "復活邪神 Re ; universe",
      "popularity": 3178,
      "article": 7,
      "bsn": 35284,
      "board_url": "https://forum.gamer.com.tw/B.php?bsn=35284",
      "category_slug": "mobile",
      "category_label": "手機遊戲哈啦區"
    },
    {
      "rank": 95,
      "title": "遺忘之劍",
      "popularity": 3169,
      "article": 0,
      "bsn": 80652,
      "board_url": "https://forum.gamer.com.tw/B.php?bsn=80652",
      "category_slug": "mobile",
      "category_label": "手機遊戲哈啦區"
    },
    {
      "rank": 96,
      "title": "問答 RPG 魔法使與黑貓維茲",
      "popularity": 3085,
      "article": 4,
      "bsn": 25730,
      "board_url": "https://forum.gamer.com.tw/B.php?bsn=25730",
      "category_slug": "mobile",
      "category_label": "手機遊戲哈啦區"
    },
    {
      "rank": 97,
      "title": "薑餅人王國",
      "popularity": 2889,
      "article": 7,
      "bsn": 70199,
      "board_url": "https://forum.gamer.com.tw/B.php?bsn=70199",
      "category_slug": "mobile",
      "category_label": "手機遊戲哈啦區"
    },
    {
      "rank": 98,
      "title": "塵白禁域",
      "popularity": 2882,
      "article": 0,
      "bsn": 72111,
      "board_url": "https://forum.gamer.com.tw/B.php?bsn=72111",
      "category_slug": "mobile",
      "category_label": "手機遊戲哈啦區"
    },
    {
      "rank": 99,
      "title": "RAID : Shadow Legends",
      "popularity": 2858,
      "article": 3,
      "bsn": 36208,
      "board_url": "https://forum.gamer.com.tw/B.php?bsn=36208",
      "category_slug": "mobile",
      "category_label": "手機遊戲哈啦區"
    },
    {
      "rank": 100,
      "title": "忍者喵喵：保衛村莊",
      "popularity": 2854,
      "article": 0,
      "bsn": 80326,
      "board_url": "https://forum.gamer.com.tw/B.php?bsn=80326",
      "category_slug": "mobile",
      "category_label": "手機遊戲哈啦區"
    },
    {
      "rank": 101,
      "title": "全民打棒球 Pro",
      "popularity": 2835,
      "article": 3,
      "bsn": 39283,
      "board_url": "https://forum.gamer.com.tw/B.php?bsn=39283",
      "category_slug": "mobile",
      "category_label": "手機遊戲哈啦區"
    },
    {
      "rank": 102,
      "title": "魔御：STAR DIVE",
      "popularity": 2825,
      "article": 3,
      "bsn": 81457,
      "board_url": "https://forum.gamer.com.tw/B.php?bsn=81457",
      "category_slug": "mobile",
      "category_label": "手機遊戲哈啦區"
    },
    {
      "rank": 103,
      "title": "歧路旅人：大陸的霸者",
      "popularity": 2751,
      "article": 0,
      "bsn": 36225,
      "board_url": "https://forum.gamer.com.tw/B.php?bsn=36225",
      "category_slug": "mobile",
      "category_label": "手機遊戲哈啦區"
    },
    {
      "rank": 104,
      "title": "三國：謀定天下",
      "popularity": 2691,
      "article": 0,
      "bsn": 83812,
      "board_url": "https://forum.gamer.com.tw/B.php?bsn=83812",
      "category_slug": "mobile",
      "category_label": "手機遊戲哈啦區"
    },
    {
      "rank": 105,
      "title": "暗黑破壞神：永生不朽",
      "popularity": 2667,
      "article": 0,
      "bsn": 35531,
      "board_url": "https://forum.gamer.com.tw/B.php?bsn=35531",
      "category_slug": "mobile",
      "category_label": "手機遊戲哈啦區"
    },
    {
      "rank": 106,
      "title": "鎖鏈戰記 CHAIN CHRONICLE",
      "popularity": 2652,
      "article": 3,
      "bsn": 24520,
      "board_url": "https://forum.gamer.com.tw/B.php?bsn=24520",
      "category_slug": "mobile",
      "category_label": "手機遊戲哈啦區"
    },
    {
      "rank": 107,
      "title": "怪獸 8 號 THE GAME",
      "popularity": 2643,
      "article": 2,
      "bsn": 81768,
      "board_url": "https://forum.gamer.com.tw/B.php?bsn=81768",
      "category_slug": "mobile",
      "category_label": "手機遊戲哈啦區"
    },
    {
      "rank": 108,
      "title": "同盟塔防戰",
      "popularity": 2637,
      "article": 1,
      "bsn": 81508,
      "board_url": "https://forum.gamer.com.tw/B.php?bsn=81508",
      "category_slug": "mobile",
      "category_label": "手機遊戲哈啦區"
    },
    {
      "rank": 109,
      "title": "Dungeon Slasher",
      "popularity": 2601,
      "article": 1,
      "bsn": 79453,
      "board_url": "https://forum.gamer.com.tw/B.php?bsn=79453",
      "category_slug": "mobile",
      "category_label": "手機遊戲哈啦區"
    },
    {
      "rank": 110,
      "title": "遊戲王 決鬥聯盟",
      "popularity": 2544,
      "article": 5,
      "bsn": 29618,
      "board_url": "https://forum.gamer.com.tw/B.php?bsn=29618",
      "category_slug": "mobile",
      "category_label": "手機遊戲哈啦區"
    },
    {
      "rank": 111,
      "title": "BLEACH 死神 Brave Souls",
      "popularity": 2543,
      "article": 2,
      "bsn": 27808,
      "board_url": "https://forum.gamer.com.tw/B.php?bsn=27808",
      "category_slug": "mobile",
      "category_label": "手機遊戲哈啦區"
    },
    {
      "rank": 112,
      "title": "劍與遠征：啟程",
      "popularity": 2448,
      "article": 0,
      "bsn": 75975,
      "board_url": "https://forum.gamer.com.tw/B.php?bsn=75975",
      "category_slug": "mobile",
      "category_label": "手機遊戲哈啦區"
    },
    {
      "rank": 113,
      "title": "克魯賽德戰記 Crusaders Quest",
      "popularity": 2399,
      "article": 0,
      "bsn": 27586,
      "board_url": "https://forum.gamer.com.tw/B.php?bsn=27586",
      "category_slug": "mobile",
      "category_label": "手機遊戲哈啦區"
    },
    {
      "rank": 114,
      "title": "守望傳說 Guardian Tales",
      "popularity": 2376,
      "article": 1,
      "bsn": 38113,
      "board_url": "https://forum.gamer.com.tw/B.php?bsn=38113",
      "category_slug": "mobile",
      "category_label": "手機遊戲哈啦區"
    },
    {
      "rank": 115,
      "title": "RO仙境傳說：守護永恆的愛",
      "popularity": 2296,
      "article": 1,
      "bsn": 28924,
      "board_url": "https://forum.gamer.com.tw/B.php?bsn=28924",
      "category_slug": "mobile",
      "category_label": "手機遊戲哈啦區"
    },
    {
      "rank": 116,
      "title": "卡皮巴拉 Go",
      "popularity": 2284,
      "article": 1,
      "bsn": 81254,
      "board_url": "https://forum.gamer.com.tw/B.php?bsn=81254",
      "category_slug": "mobile",
      "category_label": "手機遊戲哈啦區"
    },
    {
      "rank": 117,
      "title": "戰雙帕彌什",
      "popularity": 2268,
      "article": 2,
      "bsn": 37463,
      "board_url": "https://forum.gamer.com.tw/B.php?bsn=37463",
      "category_slug": "mobile",
      "category_label": "手機遊戲哈啦區"
    },
    {
      "rank": 118,
      "title": "英雄聯盟：聯盟戰棋",
      "popularity": 2240,
      "article": 1,
      "bsn": 38053,
      "board_url": "https://forum.gamer.com.tw/B.php?bsn=38053",
      "category_slug": "mobile",
      "category_label": "手機遊戲哈啦區"
    },
    {
      "rank": 119,
      "title": "七大罪：Origin",
      "popularity": 2225,
      "article": 0,
      "bsn": 74141,
      "board_url": "https://forum.gamer.com.tw/B.php?bsn=74141",
      "category_slug": "mobile",
      "category_label": "手機遊戲哈啦區"
    },
    {
      "rank": 120,
      "title": "地牢深處 Dungeon Within",
      "popularity": 2201,
      "article": 0,
      "bsn": 85358,
      "board_url": "https://forum.gamer.com.tw/B.php?bsn=85358",
      "category_slug": "mobile",
      "category_label": "手機遊戲哈啦區"
    }
  ]
}
