{
  "generated_at": "2026-05-04",
  "source_url": "https://forum.gamer.com.tw/",
  "category": {
    "slug": "mobile",
    "label": "手機遊戲哈啦區",
    "board_count": 120
  },
  "boards": [
    {
      "rank": 1,
      "title": "異環",
      "popularity": 571064,
      "article": 679,
      "bsn": 80679,
      "board_url": "https://forum.gamer.com.tw/B.php?bsn=80679",
      "category_slug": "mobile",
      "category_label": "手機遊戲哈啦區"
    },
    {
      "rank": 2,
      "title": "鳴潮",
      "popularity": 261513,
      "article": 311,
      "bsn": 74934,
      "board_url": "https://forum.gamer.com.tw/B.php?bsn=74934",
      "category_slug": "mobile",
      "category_label": "手機遊戲哈啦區"
    },
    {
      "rank": 3,
      "title": "SD 鋼彈 G 世代 永恆",
      "popularity": 152688,
      "article": 59,
      "bsn": 74906,
      "board_url": "https://forum.gamer.com.tw/B.php?bsn=74906",
      "category_slug": "mobile",
      "category_label": "手機遊戲哈啦區"
    },
    {
      "rank": 4,
      "title": "卡厄思夢境",
      "popularity": 126559,
      "article": 82,
      "bsn": 80099,
      "board_url": "https://forum.gamer.com.tw/B.php?bsn=80099",
      "category_slug": "mobile",
      "category_label": "手機遊戲哈啦區"
    },
    {
      "rank": 5,
      "title": "勇者鬥惡龍 破限亂鬥",
      "popularity": 123812,
      "article": 39,
      "bsn": 83661,
      "board_url": "https://forum.gamer.com.tw/B.php?bsn=83661",
      "category_slug": "mobile",
      "category_label": "手機遊戲哈啦區"
    },
    {
      "rank": 6,
      "title": "勝利女神：妮姬",
      "popularity": 102867,
      "article": 79,
      "bsn": 36390,
      "board_url": "https://forum.gamer.com.tw/B.php?bsn=36390",
      "category_slug": "mobile",
      "category_label": "手機遊戲哈啦區"
    },
    {
      "rank": 7,
      "title": "崩壞：星穹鐵道",
      "popularity": 92731,
      "article": 78,
      "bsn": 72822,
      "board_url": "https://forum.gamer.com.tw/B.php?bsn=72822",
      "category_slug": "mobile",
      "category_label": "手機遊戲哈啦區"
    },
    {
      "rank": 8,
      "title": "棕色塵埃 2",
      "popularity": 82294,
      "article": 29,
      "bsn": 76207,
      "board_url": "https://forum.gamer.com.tw/B.php?bsn=76207",
      "category_slug": "mobile",
      "category_label": "手機遊戲哈啦區"
    },
    {
      "rank": 9,
      "title": "神魔之塔",
      "popularity": 80022,
      "article": 61,
      "bsn": 23805,
      "board_url": "https://forum.gamer.com.tw/B.php?bsn=23805",
      "category_slug": "mobile",
      "category_label": "手機遊戲哈啦區"
    },
    {
      "rank": 10,
      "title": "Fate/Grand Order",
      "popularity": 66621,
      "article": 50,
      "bsn": 26742,
      "board_url": "https://forum.gamer.com.tw/B.php?bsn=26742",
      "category_slug": "mobile",
      "category_label": "手機遊戲哈啦區"
    },
    {
      "rank": 11,
      "title": "貓咪大戰爭（にゃんこ大戦争）",
      "popularity": 63769,
      "article": 3,
      "bsn": 23772,
      "board_url": "https://forum.gamer.com.tw/B.php?bsn=23772",
      "category_slug": "mobile",
      "category_label": "手機遊戲哈啦區"
    },
    {
      "rank": 12,
      "title": "明日方舟：終末地",
      "popularity": 59632,
      "article": 34,
      "bsn": 74604,
      "board_url": "https://forum.gamer.com.tw/B.php?bsn=74604",
      "category_slug": "mobile",
      "category_label": "手機遊戲哈啦區"
    },
    {
      "rank": 13,
      "title": "原神",
      "popularity": 52820,
      "article": 30,
      "bsn": 36730,
      "board_url": "https://forum.gamer.com.tw/B.php?bsn=36730",
      "category_slug": "mobile",
      "category_label": "手機遊戲哈啦區"
    },
    {
      "rank": 14,
      "title": "辟邪除妖 Variants Daphne",
      "popularity": 49062,
      "article": 25,
      "bsn": 70180,
      "board_url": "https://forum.gamer.com.tw/B.php?bsn=70180",
      "category_slug": "mobile",
      "category_label": "手機遊戲哈啦區"
    },
    {
      "rank": 15,
      "title": "點點英雄：骰子傳說",
      "popularity": 44441,
      "article": 18,
      "bsn": 85135,
      "board_url": "https://forum.gamer.com.tw/B.php?bsn=85135",
      "category_slug": "mobile",
      "category_label": "手機遊戲哈啦區"
    },
    {
      "rank": 16,
      "title": "絕區零",
      "popularity": 43488,
      "article": 19,
      "bsn": 74860,
      "board_url": "https://forum.gamer.com.tw/B.php?bsn=74860",
      "category_slug": "mobile",
      "category_label": "手機遊戲哈啦區"
    },
    {
      "rank": 17,
      "title": "天堂 Mobile",
      "popularity": 40731,
      "article": 11,
      "bsn": 25908,
      "board_url": "https://forum.gamer.com.tw/B.php?bsn=25908",
      "category_slug": "mobile",
      "category_label": "手機遊戲哈啦區"
    },
    {
      "rank": 18,
      "title": "Pikmin Bloom",
      "popularity": 39600,
      "article": 19,
      "bsn": 72889,
      "board_url": "https://forum.gamer.com.tw/B.php?bsn=72889",
      "category_slug": "mobile",
      "category_label": "手機遊戲哈啦區"
    },
    {
      "rank": 19,
      "title": "闇影詩章 Shadowverse",
      "popularity": 36457,
      "article": 38,
      "bsn": 29330,
      "board_url": "https://forum.gamer.com.tw/B.php?bsn=29330",
      "category_slug": "mobile",
      "category_label": "手機遊戲哈啦區"
    },
    {
      "rank": 20,
      "title": "RO 仙境傳說：世界之旅",
      "popularity": 33851,
      "article": 11,
      "bsn": 83054,
      "board_url": "https://forum.gamer.com.tw/B.php?bsn=83054",
      "category_slug": "mobile",
      "category_label": "手機遊戲哈啦區"
    },
    {
      "rank": 21,
      "title": "寶可夢集換式卡牌遊戲口袋版",
      "popularity": 31958,
      "article": 74,
      "bsn": 79688,
      "board_url": "https://forum.gamer.com.tw/B.php?bsn=79688",
      "category_slug": "mobile",
      "category_label": "手機遊戲哈啦區"
    },
    {
      "rank": 22,
      "title": "傳說對決 Arena of Valor",
      "popularity": 30691,
      "article": 297,
      "bsn": 30518,
      "board_url": "https://forum.gamer.com.tw/B.php?bsn=30518",
      "category_slug": "mobile",
      "category_label": "手機遊戲哈啦區"
    },
    {
      "rank": 23,
      "title": "蔚藍檔案",
      "popularity": 27027,
      "article": 8,
      "bsn": 38898,
      "board_url": "https://forum.gamer.com.tw/B.php?bsn=38898",
      "category_slug": "mobile",
      "category_label": "手機遊戲哈啦區"
    },
    {
      "rank": 24,
      "title": "怪物彈珠",
      "popularity": 25038,
      "article": 29,
      "bsn": 25052,
      "board_url": "https://forum.gamer.com.tw/B.php?bsn=25052",
      "category_slug": "mobile",
      "category_label": "手機遊戲哈啦區"
    },
    {
      "rank": 25,
      "title": "明日方舟",
      "popularity": 24412,
      "article": 24,
      "bsn": 33651,
      "board_url": "https://forum.gamer.com.tw/B.php?bsn=33651",
      "category_slug": "mobile",
      "category_label": "手機遊戲哈啦區"
    },
    {
      "rank": 26,
      "title": "Monster Hunter Now",
      "popularity": 21140,
      "article": 7,
      "bsn": 77414,
      "board_url": "https://forum.gamer.com.tw/B.php?bsn=77414",
      "category_slug": "mobile",
      "category_label": "手機遊戲哈啦區"
    },
    {
      "rank": 27,
      "title": "Pokemon GO",
      "popularity": 19852,
      "article": 2,
      "bsn": 29659,
      "board_url": "https://forum.gamer.com.tw/B.php?bsn=29659",
      "category_slug": "mobile",
      "category_label": "手機遊戲哈啦區"
    },
    {
      "rank": 28,
      "title": "超異域公主連結☆Re:Dive",
      "popularity": 18303,
      "article": 48,
      "bsn": 30861,
      "board_url": "https://forum.gamer.com.tw/B.php?bsn=30861",
      "category_slug": "mobile",
      "category_label": "手機遊戲哈啦區"
    },
    {
      "rank": 29,
      "title": "劍與遠征：啟程",
      "popularity": 18296,
      "article": 6,
      "bsn": 75975,
      "board_url": "https://forum.gamer.com.tw/B.php?bsn=75975",
      "category_slug": "mobile",
      "category_label": "手機遊戲哈啦區"
    },
    {
      "rank": 30,
      "title": "無盡輪迴：鬼域摸金",
      "popularity": 15122,
      "article": 21,
      "bsn": 85166,
      "board_url": "https://forum.gamer.com.tw/B.php?bsn=85166",
      "category_slug": "mobile",
      "category_label": "手機遊戲哈啦區"
    },
    {
      "rank": 31,
      "title": "楓之谷：放置冒險記",
      "popularity": 13917,
      "article": 2,
      "bsn": 82899,
      "board_url": "https://forum.gamer.com.tw/B.php?bsn=82899",
      "category_slug": "mobile",
      "category_label": "手機遊戲哈啦區"
    },
    {
      "rank": 32,
      "title": "少女前線 2：追放",
      "popularity": 13815,
      "article": 36,
      "bsn": 70502,
      "board_url": "https://forum.gamer.com.tw/B.php?bsn=70502",
      "category_slug": "mobile",
      "category_label": "手機遊戲哈啦區"
    },
    {
      "rank": 33,
      "title": "心動小鎮",
      "popularity": 13702,
      "article": 5,
      "bsn": 75403,
      "board_url": "https://forum.gamer.com.tw/B.php?bsn=75403",
      "category_slug": "mobile",
      "category_label": "手機遊戲哈啦區"
    },
    {
      "rank": 34,
      "title": "煙雨江湖",
      "popularity": 12684,
      "article": 3,
      "bsn": 71402,
      "board_url": "https://forum.gamer.com.tw/B.php?bsn=71402",
      "category_slug": "mobile",
      "category_label": "手機遊戲哈啦區"
    },
    {
      "rank": 35,
      "title": "魔御：STAR DIVE",
      "popularity": 12296,
      "article": 10,
      "bsn": 81457,
      "board_url": "https://forum.gamer.com.tw/B.php?bsn=81457",
      "category_slug": "mobile",
      "category_label": "手機遊戲哈啦區"
    },
    {
      "rank": 36,
      "title": "楓之谷 M",
      "popularity": 12249,
      "article": 4,
      "bsn": 29461,
      "board_url": "https://forum.gamer.com.tw/B.php?bsn=29461",
      "category_slug": "mobile",
      "category_label": "手機遊戲哈啦區"
    },
    {
      "rank": 37,
      "title": "三國志•戰略版",
      "popularity": 12051,
      "article": 0,
      "bsn": 36815,
      "board_url": "https://forum.gamer.com.tw/B.php?bsn=36815",
      "category_slug": "mobile",
      "category_label": "手機遊戲哈啦區"
    },
    {
      "rank": 38,
      "title": "緋染天空 Heaven Burns Red",
      "popularity": 11876,
      "article": 23,
      "bsn": 37697,
      "board_url": "https://forum.gamer.com.tw/B.php?bsn=37697",
      "category_slug": "mobile",
      "category_label": "手機遊戲哈啦區"
    },
    {
      "rank": 39,
      "title": "天堂 W",
      "popularity": 11569,
      "article": 2,
      "bsn": 71905,
      "board_url": "https://forum.gamer.com.tw/B.php?bsn=71905",
      "category_slug": "mobile",
      "category_label": "手機遊戲哈啦區"
    },
    {
      "rank": 40,
      "title": "碧藍航線",
      "popularity": 10868,
      "article": 4,
      "bsn": 32550,
      "board_url": "https://forum.gamer.com.tw/B.php?bsn=32550",
      "category_slug": "mobile",
      "category_label": "手機遊戲哈啦區"
    },
    {
      "rank": 41,
      "title": "Another Eden：穿越時空的貓",
      "popularity": 10832,
      "article": 4,
      "bsn": 29220,
      "board_url": "https://forum.gamer.com.tw/B.php?bsn=29220",
      "category_slug": "mobile",
      "category_label": "手機遊戲哈啦區"
    },
    {
      "rank": 42,
      "title": "全境封鎖：曙光",
      "popularity": 10695,
      "article": 11,
      "bsn": 75244,
      "board_url": "https://forum.gamer.com.tw/B.php?bsn=75244",
      "category_slug": "mobile",
      "category_label": "手機遊戲哈啦區"
    },
    {
      "rank": 43,
      "title": "女神異聞錄：夜幕魅影",
      "popularity": 9803,
      "article": 10,
      "bsn": 71034,
      "board_url": "https://forum.gamer.com.tw/B.php?bsn=71034",
      "category_slug": "mobile",
      "category_label": "手機遊戲哈啦區"
    },
    {
      "rank": 44,
      "title": "星塔旅人",
      "popularity": 9745,
      "article": 5,
      "bsn": 81566,
      "board_url": "https://forum.gamer.com.tw/B.php?bsn=81566",
      "category_slug": "mobile",
      "category_label": "手機遊戲哈啦區"
    },
    {
      "rank": 45,
      "title": "MLB：9 局職棒 系列",
      "popularity": 9608,
      "article": 4,
      "bsn": 31114,
      "board_url": "https://forum.gamer.com.tw/B.php?bsn=31114",
      "category_slug": "mobile",
      "category_label": "手機遊戲哈啦區"
    },
    {
      "rank": 46,
      "title": "七騎士 RE:BIRTH",
      "popularity": 9496,
      "article": 10,
      "bsn": 79741,
      "board_url": "https://forum.gamer.com.tw/B.php?bsn=79741",
      "category_slug": "mobile",
      "category_label": "手機遊戲哈啦區"
    },
    {
      "rank": 47,
      "title": "賽馬娘Pretty Derby",
      "popularity": 9270,
      "article": 14,
      "bsn": 34421,
      "board_url": "https://forum.gamer.com.tw/B.php?bsn=34421",
      "category_slug": "mobile",
      "category_label": "手機遊戲哈啦區"
    },
    {
      "rank": 48,
      "title": "七大罪：Origin",
      "popularity": 8779,
      "article": 4,
      "bsn": 74141,
      "board_url": "https://forum.gamer.com.tw/B.php?bsn=74141",
      "category_slug": "mobile",
      "category_label": "手機遊戲哈啦區"
    },
    {
      "rank": 49,
      "title": "Pokémon Sleep",
      "popularity": 8659,
      "article": 21,
      "bsn": 36685,
      "board_url": "https://forum.gamer.com.tw/B.php?bsn=36685",
      "category_slug": "mobile",
      "category_label": "手機遊戲哈啦區"
    },
    {
      "rank": 50,
      "title": "夢幻模擬戰 手機版",
      "popularity": 8144,
      "article": 4,
      "bsn": 33596,
      "board_url": "https://forum.gamer.com.tw/B.php?bsn=33596",
      "category_slug": "mobile",
      "category_label": "手機遊戲哈啦區"
    },
    {
      "rank": 51,
      "title": "寒霜啟示錄",
      "popularity": 7947,
      "article": 0,
      "bsn": 76999,
      "board_url": "https://forum.gamer.com.tw/B.php?bsn=76999",
      "category_slug": "mobile",
      "category_label": "手機遊戲哈啦區"
    },
    {
      "rank": 52,
      "title": "第七史詩",
      "popularity": 7931,
      "article": 4,
      "bsn": 34880,
      "board_url": "https://forum.gamer.com.tw/B.php?bsn=34880",
      "category_slug": "mobile",
      "category_label": "手機遊戲哈啦區"
    },
    {
      "rank": 53,
      "title": "荒野亂鬥",
      "popularity": 7776,
      "article": 4,
      "bsn": 32407,
      "board_url": "https://forum.gamer.com.tw/B.php?bsn=32407",
      "category_slug": "mobile",
      "category_label": "手機遊戲哈啦區"
    },
    {
      "rank": 54,
      "title": "信長之野望 真戰",
      "popularity": 7489,
      "article": 10,
      "bsn": 82869,
      "board_url": "https://forum.gamer.com.tw/B.php?bsn=82869",
      "category_slug": "mobile",
      "category_label": "手機遊戲哈啦區"
    },
    {
      "rank": 55,
      "title": "杖劍傳說：坎斯汀之約",
      "popularity": 7295,
      "article": 0,
      "bsn": 80389,
      "board_url": "https://forum.gamer.com.tw/B.php?bsn=80389",
      "category_slug": "mobile",
      "category_label": "手機遊戲哈啦區"
    },
    {
      "rank": 56,
      "title": "魔靈召喚",
      "popularity": 6729,
      "article": 5,
      "bsn": 26380,
      "board_url": "https://forum.gamer.com.tw/B.php?bsn=26380",
      "category_slug": "mobile",
      "category_label": "手機遊戲哈啦區"
    },
    {
      "rank": 57,
      "title": "重返未來：1999",
      "popularity": 6715,
      "article": 1,
      "bsn": 75028,
      "board_url": "https://forum.gamer.com.tw/B.php?bsn=75028",
      "category_slug": "mobile",
      "category_label": "手機遊戲哈啦區"
    },
    {
      "rank": 58,
      "title": "嘟嘟臉惡作劇",
      "popularity": 6686,
      "article": 4,
      "bsn": 78781,
      "board_url": "https://forum.gamer.com.tw/B.php?bsn=78781",
      "category_slug": "mobile",
      "category_label": "手機遊戲哈啦區"
    },
    {
      "rank": 59,
      "title": "星之救援者 StarSavior",
      "popularity": 6469,
      "article": 4,
      "bsn": 81995,
      "board_url": "https://forum.gamer.com.tw/B.php?bsn=81995",
      "category_slug": "mobile",
      "category_label": "手機遊戲哈啦區"
    },
    {
      "rank": 60,
      "title": "三國：謀定天下",
      "popularity": 6360,
      "article": 0,
      "bsn": 83812,
      "board_url": "https://forum.gamer.com.tw/B.php?bsn=83812",
      "category_slug": "mobile",
      "category_label": "手機遊戲哈啦區"
    },
    {
      "rank": 61,
      "title": "Kingshot",
      "popularity": 6260,
      "article": 0,
      "bsn": 82382,
      "board_url": "https://forum.gamer.com.tw/B.php?bsn=82382",
      "category_slug": "mobile",
      "category_label": "手機遊戲哈啦區"
    },
    {
      "rank": 62,
      "title": "塵白禁域",
      "popularity": 6205,
      "article": 2,
      "bsn": 72111,
      "board_url": "https://forum.gamer.com.tw/B.php?bsn=72111",
      "category_slug": "mobile",
      "category_label": "手機遊戲哈啦區"
    },
    {
      "rank": 63,
      "title": "運氣拼輸贏",
      "popularity": 6088,
      "article": 5,
      "bsn": 80385,
      "board_url": "https://forum.gamer.com.tw/B.php?bsn=80385",
      "category_slug": "mobile",
      "category_label": "手機遊戲哈啦區"
    },
    {
      "rank": 64,
      "title": "鈴蘭之劍：爲這和平的世界",
      "popularity": 5798,
      "article": 1,
      "bsn": 71838,
      "board_url": "https://forum.gamer.com.tw/B.php?bsn=71838",
      "category_slug": "mobile",
      "category_label": "手機遊戲哈啦區"
    },
    {
      "rank": 65,
      "title": "Rogue with the Dead - 亡途轉生",
      "popularity": 5665,
      "article": 2,
      "bsn": 81808,
      "board_url": "https://forum.gamer.com.tw/B.php?bsn=81808",
      "category_slug": "mobile",
      "category_label": "手機遊戲哈啦區"
    },
    {
      "rank": 66,
      "title": "逆水寒",
      "popularity": 5605,
      "article": 1,
      "bsn": 77001,
      "board_url": "https://forum.gamer.com.tw/B.php?bsn=77001",
      "category_slug": "mobile",
      "category_label": "手機遊戲哈啦區"
    },
    {
      "rank": 67,
      "title": "RO 仙境傳說：愛如初見 Classic",
      "popularity": 5394,
      "article": 8,
      "bsn": 84500,
      "board_url": "https://forum.gamer.com.tw/B.php?bsn=84500",
      "category_slug": "mobile",
      "category_label": "手機遊戲哈啦區"
    },
    {
      "rank": 68,
      "title": "地牢深處 Dungeon Within",
      "popularity": 5342,
      "article": 0,
      "bsn": 85358,
      "board_url": "https://forum.gamer.com.tw/B.php?bsn=85358",
      "category_slug": "mobile",
      "category_label": "手機遊戲哈啦區"
    },
    {
      "rank": 69,
      "title": "碧藍幻想 系列",
      "popularity": 5319,
      "article": 14,
      "bsn": 25204,
      "board_url": "https://forum.gamer.com.tw/B.php?bsn=25204",
      "category_slug": "mobile",
      "category_label": "手機遊戲哈啦區"
    },
    {
      "rank": 70,
      "title": "XXL 猛漢町",
      "popularity": 5191,
      "article": 1,
      "bsn": 80107,
      "board_url": "https://forum.gamer.com.tw/B.php?bsn=80107",
      "category_slug": "mobile",
      "category_label": "手機遊戲哈啦區"
    },
    {
      "rank": 71,
      "title": "寶可夢大師",
      "popularity": 5176,
      "article": 1,
      "bsn": 36673,
      "board_url": "https://forum.gamer.com.tw/B.php?bsn=36673",
      "category_slug": "mobile",
      "category_label": "手機遊戲哈啦區"
    },
    {
      "rank": 72,
      "title": "守望傳說 Guardian Tales",
      "popularity": 5096,
      "article": 4,
      "bsn": 38113,
      "board_url": "https://forum.gamer.com.tw/B.php?bsn=38113",
      "category_slug": "mobile",
      "category_label": "手機遊戲哈啦區"
    },
    {
      "rank": 73,
      "title": "新熱血江湖：世界",
      "popularity": 4881,
      "article": 1,
      "bsn": 84232,
      "board_url": "https://forum.gamer.com.tw/B.php?bsn=84232",
      "category_slug": "mobile",
      "category_label": "手機遊戲哈啦區"
    },
    {
      "rank": 74,
      "title": "天地劫 手機版",
      "popularity": 4816,
      "article": 3,
      "bsn": 38462,
      "board_url": "https://forum.gamer.com.tw/B.php?bsn=38462",
      "category_slug": "mobile",
      "category_label": "手機遊戲哈啦區"
    },
    {
      "rank": 75,
      "title": "英雄聯盟：聯盟戰棋",
      "popularity": 4800,
      "article": 1,
      "bsn": 38053,
      "board_url": "https://forum.gamer.com.tw/B.php?bsn=38053",
      "category_slug": "mobile",
      "category_label": "手機遊戲哈啦區"
    },
    {
      "rank": 76,
      "title": "世界計畫 繽紛舞台！ feat. 初音未來",
      "popularity": 4660,
      "article": 0,
      "bsn": 37505,
      "board_url": "https://forum.gamer.com.tw/B.php?bsn=37505",
      "category_slug": "mobile",
      "category_label": "手機遊戲哈啦區"
    },
    {
      "rank": 77,
      "title": "龍族拼圖 Puzzle & Dragons",
      "popularity": 4651,
      "article": 1,
      "bsn": 22153,
      "board_url": "https://forum.gamer.com.tw/B.php?bsn=22153",
      "category_slug": "mobile",
      "category_label": "手機遊戲哈啦區"
    },
    {
      "rank": 78,
      "title": "最後的克勞迪亞",
      "popularity": 4539,
      "article": 0,
      "bsn": 35735,
      "board_url": "https://forum.gamer.com.tw/B.php?bsn=35735",
      "category_slug": "mobile",
      "category_label": "手機遊戲哈啦區"
    },
    {
      "rank": 79,
      "title": "同盟塔防戰",
      "popularity": 4349,
      "article": 4,
      "bsn": 81508,
      "board_url": "https://forum.gamer.com.tw/B.php?bsn=81508",
      "category_slug": "mobile",
      "category_label": "手機遊戲哈啦區"
    },
    {
      "rank": 80,
      "title": "薑餅人王國",
      "popularity": 4187,
      "article": 2,
      "bsn": 70199,
      "board_url": "https://forum.gamer.com.tw/B.php?bsn=70199",
      "category_slug": "mobile",
      "category_label": "手機遊戲哈啦區"
    },
    {
      "rank": 81,
      "title": "RO 新世代：攜手同行",
      "popularity": 4109,
      "article": 1,
      "bsn": 37030,
      "board_url": "https://forum.gamer.com.tw/B.php?bsn=37030",
      "category_slug": "mobile",
      "category_label": "手機遊戲哈啦區"
    },
    {
      "rank": 82,
      "title": "Limbus Company",
      "popularity": 4098,
      "article": 1,
      "bsn": 73052,
      "board_url": "https://forum.gamer.com.tw/B.php?bsn=73052",
      "category_slug": "mobile",
      "category_label": "手機遊戲哈啦區"
    },
    {
      "rank": 83,
      "title": "白貓 Project",
      "popularity": 3812,
      "article": 2,
      "bsn": 26686,
      "board_url": "https://forum.gamer.com.tw/B.php?bsn=26686",
      "category_slug": "mobile",
      "category_label": "手機遊戲哈啦區"
    },
    {
      "rank": 84,
      "title": "MLB 勁旅對決",
      "popularity": 3773,
      "article": 4,
      "bsn": 77583,
      "board_url": "https://forum.gamer.com.tw/B.php?bsn=77583",
      "category_slug": "mobile",
      "category_label": "手機遊戲哈啦區"
    },
    {
      "rank": 85,
      "title": "BanG Dream！少女樂團派對",
      "popularity": 3625,
      "article": 10,
      "bsn": 31877,
      "board_url": "https://forum.gamer.com.tw/B.php?bsn=31877",
      "category_slug": "mobile",
      "category_label": "手機遊戲哈啦區"
    },
    {
      "rank": 86,
      "title": "DRAGON BALL Z -七龍珠爆裂激戰-",
      "popularity": 3565,
      "article": 0,
      "bsn": 27096,
      "board_url": "https://forum.gamer.com.tw/B.php?bsn=27096",
      "category_slug": "mobile",
      "category_label": "手機遊戲哈啦區"
    },
    {
      "rank": 87,
      "title": "忘卻前夜 Morimens",
      "popularity": 3508,
      "article": 1,
      "bsn": 78829,
      "board_url": "https://forum.gamer.com.tw/B.php?bsn=78829",
      "category_slug": "mobile",
      "category_label": "手機遊戲哈啦區"
    },
    {
      "rank": 88,
      "title": "召喚圖板 Summons Board",
      "popularity": 3466,
      "article": 5,
      "bsn": 25691,
      "board_url": "https://forum.gamer.com.tw/B.php?bsn=25691",
      "category_slug": "mobile",
      "category_label": "手機遊戲哈啦區"
    },
    {
      "rank": 89,
      "title": "跑跑薑餅人：烤箱大逃亡",
      "popularity": 3430,
      "article": 8,
      "bsn": 31023,
      "board_url": "https://forum.gamer.com.tw/B.php?bsn=31023",
      "category_slug": "mobile",
      "category_label": "手機遊戲哈啦區"
    },
    {
      "rank": 90,
      "title": "蔚藍星球：國王很忙",
      "popularity": 3428,
      "article": 3,
      "bsn": 83538,
      "board_url": "https://forum.gamer.com.tw/B.php?bsn=83538",
      "category_slug": "mobile",
      "category_label": "手機遊戲哈啦區"
    },
    {
      "rank": 91,
      "title": "忍者喵喵：保衛村莊",
      "popularity": 3244,
      "article": 3,
      "bsn": 80326,
      "board_url": "https://forum.gamer.com.tw/B.php?bsn=80326",
      "category_slug": "mobile",
      "category_label": "手機遊戲哈啦區"
    },
    {
      "rank": 92,
      "title": "卡皮巴拉 Go",
      "popularity": 3236,
      "article": 0,
      "bsn": 81254,
      "board_url": "https://forum.gamer.com.tw/B.php?bsn=81254",
      "category_slug": "mobile",
      "category_label": "手機遊戲哈啦區"
    },
    {
      "rank": 93,
      "title": "Bleach：刀鳴",
      "popularity": 3178,
      "article": 3,
      "bsn": 78017,
      "board_url": "https://forum.gamer.com.tw/B.php?bsn=78017",
      "category_slug": "mobile",
      "category_label": "手機遊戲哈啦區"
    },
    {
      "rank": 94,
      "title": "LINE Rangers 銀河特攻隊",
      "popularity": 3081,
      "article": 2,
      "bsn": 25967,
      "board_url": "https://forum.gamer.com.tw/B.php?bsn=25967",
      "category_slug": "mobile",
      "category_label": "手機遊戲哈啦區"
    },
    {
      "rank": 95,
      "title": "遊戲王 決鬥聯盟",
      "popularity": 3031,
      "article": 1,
      "bsn": 29618,
      "board_url": "https://forum.gamer.com.tw/B.php?bsn=29618",
      "category_slug": "mobile",
      "category_label": "手機遊戲哈啦區"
    },
    {
      "rank": 96,
      "title": "問答 RPG 魔法使與黑貓維茲",
      "popularity": 3025,
      "article": 2,
      "bsn": 25730,
      "board_url": "https://forum.gamer.com.tw/B.php?bsn=25730",
      "category_slug": "mobile",
      "category_label": "手機遊戲哈啦區"
    },
    {
      "rank": 97,
      "title": "RAID : Shadow Legends",
      "popularity": 2789,
      "article": 2,
      "bsn": 36208,
      "board_url": "https://forum.gamer.com.tw/B.php?bsn=36208",
      "category_slug": "mobile",
      "category_label": "手機遊戲哈啦區"
    },
    {
      "rank": 98,
      "title": "英雄聯盟：激鬥峽谷",
      "popularity": 2783,
      "article": 0,
      "bsn": 37459,
      "board_url": "https://forum.gamer.com.tw/B.php?bsn=37459",
      "category_slug": "mobile",
      "category_label": "手機遊戲哈啦區"
    },
    {
      "rank": 99,
      "title": "RO仙境傳說：守護永恆的愛",
      "popularity": 2748,
      "article": 0,
      "bsn": 28924,
      "board_url": "https://forum.gamer.com.tw/B.php?bsn=28924",
      "category_slug": "mobile",
      "category_label": "手機遊戲哈啦區"
    },
    {
      "rank": 100,
      "title": "歧路旅人：大陸的霸者",
      "popularity": 2700,
      "article": 1,
      "bsn": 36225,
      "board_url": "https://forum.gamer.com.tw/B.php?bsn=36225",
      "category_slug": "mobile",
      "category_label": "手機遊戲哈啦區"
    },
    {
      "rank": 101,
      "title": "魔法少女小圓 Magia Exedra（原：魔法紀錄）",
      "popularity": 2675,
      "article": 9,
      "bsn": 31057,
      "board_url": "https://forum.gamer.com.tw/B.php?bsn=31057",
      "category_slug": "mobile",
      "category_label": "手機遊戲哈啦區"
    },
    {
      "rank": 102,
      "title": "咒術迴戰 幻影夜行",
      "popularity": 2674,
      "article": 0,
      "bsn": 71515,
      "board_url": "https://forum.gamer.com.tw/B.php?bsn=71515",
      "category_slug": "mobile",
      "category_label": "手機遊戲哈啦區"
    },
    {
      "rank": 103,
      "title": "英雄傳說 卡卡布三部曲",
      "popularity": 2632,
      "article": 0,
      "bsn": 80736,
      "board_url": "https://forum.gamer.com.tw/B.php?bsn=80736",
      "category_slug": "mobile",
      "category_label": "手機遊戲哈啦區"
    },
    {
      "rank": 104,
      "title": "我想成為影之強者！Master of Garden",
      "popularity": 2620,
      "article": 1,
      "bsn": 75993,
      "board_url": "https://forum.gamer.com.tw/B.php?bsn=75993",
      "category_slug": "mobile",
      "category_label": "手機遊戲哈啦區"
    },
    {
      "rank": 105,
      "title": "弓箭傳說 系列",
      "popularity": 2584,
      "article": 1,
      "bsn": 36683,
      "board_url": "https://forum.gamer.com.tw/B.php?bsn=36683",
      "category_slug": "mobile",
      "category_label": "手機遊戲哈啦區"
    },
    {
      "rank": 106,
      "title": "崩壞 3rd",
      "popularity": 2555,
      "article": 3,
      "bsn": 31066,
      "board_url": "https://forum.gamer.com.tw/B.php?bsn=31066",
      "category_slug": "mobile",
      "category_label": "手機遊戲哈啦區"
    },
    {
      "rank": 107,
      "title": "魔力寶貝：重返法蘭",
      "popularity": 2505,
      "article": 4,
      "bsn": 84025,
      "board_url": "https://forum.gamer.com.tw/B.php?bsn=84025",
      "category_slug": "mobile",
      "category_label": "手機遊戲哈啦區"
    },
    {
      "rank": 108,
      "title": "托蘭異世錄 Toram Online RPG",
      "popularity": 2501,
      "article": 1,
      "bsn": 28271,
      "board_url": "https://forum.gamer.com.tw/B.php?bsn=28271",
      "category_slug": "mobile",
      "category_label": "手機遊戲哈啦區"
    },
    {
      "rank": 109,
      "title": "Evil Hunter Tycoon 獵魔村物語",
      "popularity": 2489,
      "article": 0,
      "bsn": 38066,
      "board_url": "https://forum.gamer.com.tw/B.php?bsn=38066",
      "category_slug": "mobile",
      "category_label": "手機遊戲哈啦區"
    },
    {
      "rank": 110,
      "title": "VAMPIR：血之繼承者",
      "popularity": 2455,
      "article": 0,
      "bsn": 83065,
      "board_url": "https://forum.gamer.com.tw/B.php?bsn=83065",
      "category_slug": "mobile",
      "category_label": "手機遊戲哈啦區"
    },
    {
      "rank": 111,
      "title": "全明星街球派對",
      "popularity": 2407,
      "article": 3,
      "bsn": 79697,
      "board_url": "https://forum.gamer.com.tw/B.php?bsn=79697",
      "category_slug": "mobile",
      "category_label": "手機遊戲哈啦區"
    },
    {
      "rank": 112,
      "title": "黑色沙漠 MOBILE",
      "popularity": 2388,
      "article": 0,
      "bsn": 32841,
      "board_url": "https://forum.gamer.com.tw/B.php?bsn=32841",
      "category_slug": "mobile",
      "category_label": "手機遊戲哈啦區"
    },
    {
      "rank": 113,
      "title": "暗黑破壞神：永生不朽",
      "popularity": 2369,
      "article": 0,
      "bsn": 35531,
      "board_url": "https://forum.gamer.com.tw/B.php?bsn=35531",
      "category_slug": "mobile",
      "category_label": "手機遊戲哈啦區"
    },
    {
      "rank": 114,
      "title": "RO仙境傳說：愛如初見（Ragnarok ORIGIN）",
      "popularity": 2354,
      "article": 0,
      "bsn": 37657,
      "board_url": "https://forum.gamer.com.tw/B.php?bsn=37657",
      "category_slug": "mobile",
      "category_label": "手機遊戲哈啦區"
    },
    {
      "rank": 115,
      "title": "遺忘之劍",
      "popularity": 2335,
      "article": 4,
      "bsn": 80652,
      "board_url": "https://forum.gamer.com.tw/B.php?bsn=80652",
      "category_slug": "mobile",
      "category_label": "手機遊戲哈啦區"
    },
    {
      "rank": 116,
      "title": "第五人格",
      "popularity": 2325,
      "article": 2,
      "bsn": 34038,
      "board_url": "https://forum.gamer.com.tw/B.php?bsn=34038",
      "category_slug": "mobile",
      "category_label": "手機遊戲哈啦區"
    },
    {
      "rank": 117,
      "title": "關於我轉生變成史萊姆這檔事 魔王與龍的建國譚",
      "popularity": 2260,
      "article": 0,
      "bsn": 70913,
      "board_url": "https://forum.gamer.com.tw/B.php?bsn=70913",
      "category_slug": "mobile",
      "category_label": "手機遊戲哈啦區"
    },
    {
      "rank": 118,
      "title": "挖你老墓",
      "popularity": 2215,
      "article": 1,
      "bsn": 85198,
      "board_url": "https://forum.gamer.com.tw/B.php?bsn=85198",
      "category_slug": "mobile",
      "category_label": "手機遊戲哈啦區"
    },
    {
      "rank": 119,
      "title": "問劍長生",
      "popularity": 2177,
      "article": 0,
      "bsn": 83086,
      "board_url": "https://forum.gamer.com.tw/B.php?bsn=83086",
      "category_slug": "mobile",
      "category_label": "手機遊戲哈啦區"
    },
    {
      "rank": 120,
      "title": "全民打棒球 Pro",
      "popularity": 2148,
      "article": 8,
      "bsn": 39283,
      "board_url": "https://forum.gamer.com.tw/B.php?bsn=39283",
      "category_slug": "mobile",
      "category_label": "手機遊戲哈啦區"
    }
  ]
}
