{
  "generated_at": "2026-06-01",
  "source_url": "https://forum.gamer.com.tw/",
  "category": {
    "slug": "pc",
    "label": "PC遊戲哈啦區",
    "board_count": 120
  },
  "boards": [
    {
      "rank": 1,
      "title": "MapleStory Worlds",
      "popularity": 248996,
      "article": 102,
      "bsn": 79354,
      "board_url": "https://forum.gamer.com.tw/B.php?bsn=79354",
      "category_slug": "pc",
      "category_label": "PC遊戲哈啦區"
    },
    {
      "rank": 2,
      "title": "流亡黯道 PoE 2",
      "popularity": 155658,
      "article": 67,
      "bsn": 82273,
      "board_url": "https://forum.gamer.com.tw/B.php?bsn=82273",
      "category_slug": "pc",
      "category_label": "PC遊戲哈啦區"
    },
    {
      "rank": 3,
      "title": "新楓之谷",
      "popularity": 118072,
      "article": 25,
      "bsn": 7650,
      "board_url": "https://forum.gamer.com.tw/B.php?bsn=7650",
      "category_slug": "pc",
      "category_label": "PC遊戲哈啦區"
    },
    {
      "rank": 4,
      "title": "燕雲十六聲",
      "popularity": 89333,
      "article": 91,
      "bsn": 75703,
      "board_url": "https://forum.gamer.com.tw/B.php?bsn=75703",
      "category_slug": "pc",
      "category_label": "PC遊戲哈啦區"
    },
    {
      "rank": 5,
      "title": "Final Fantasy XIV",
      "popularity": 81131,
      "article": 56,
      "bsn": 17608,
      "board_url": "https://forum.gamer.com.tw/B.php?bsn=17608",
      "category_slug": "pc",
      "category_label": "PC遊戲哈啦區"
    },
    {
      "rank": 6,
      "title": "天堂：經典版",
      "popularity": 71011,
      "article": 51,
      "bsn": 84452,
      "board_url": "https://forum.gamer.com.tw/B.php?bsn=84452",
      "category_slug": "pc",
      "category_label": "PC遊戲哈啦區"
    },
    {
      "rank": 7,
      "title": "暗黑破壞神 4",
      "popularity": 66308,
      "article": 36,
      "bsn": 75105,
      "board_url": "https://forum.gamer.com.tw/B.php?bsn=75105",
      "category_slug": "pc",
      "category_label": "PC遊戲哈啦區"
    },
    {
      "rank": 8,
      "title": "暗黑破壞神",
      "popularity": 58195,
      "article": 183,
      "bsn": 742,
      "board_url": "https://forum.gamer.com.tw/B.php?bsn=742",
      "category_slug": "pc",
      "category_label": "PC遊戲哈啦區"
    },
    {
      "rank": 9,
      "title": "英雄聯盟 League of Legends",
      "popularity": 54344,
      "article": 152,
      "bsn": 17532,
      "board_url": "https://forum.gamer.com.tw/B.php?bsn=17532",
      "category_slug": "pc",
      "category_label": "PC遊戲哈啦區"
    },
    {
      "rank": 10,
      "title": "RO 仙境傳說 Online",
      "popularity": 41842,
      "article": 1,
      "bsn": 4212,
      "board_url": "https://forum.gamer.com.tw/B.php?bsn=4212",
      "category_slug": "pc",
      "category_label": "PC遊戲哈啦區"
    },
    {
      "rank": 11,
      "title": "AION2",
      "popularity": 37738,
      "article": 14,
      "bsn": 82913,
      "board_url": "https://forum.gamer.com.tw/B.php?bsn=82913",
      "category_slug": "pc",
      "category_label": "PC遊戲哈啦區"
    },
    {
      "rank": 12,
      "title": "流亡黯道 Path of Exile",
      "popularity": 27844,
      "article": 3,
      "bsn": 18966,
      "board_url": "https://forum.gamer.com.tw/B.php?bsn=18966",
      "category_slug": "pc",
      "category_label": "PC遊戲哈啦區"
    },
    {
      "rank": 13,
      "title": "天使之戀Online 國際版",
      "popularity": 26254,
      "article": 9,
      "bsn": 9734,
      "board_url": "https://forum.gamer.com.tw/B.php?bsn=9734",
      "category_slug": "pc",
      "category_label": "PC遊戲哈啦區"
    },
    {
      "rank": 14,
      "title": "黑色沙漠 BLACK DESERT",
      "popularity": 25521,
      "article": 5,
      "bsn": 19017,
      "board_url": "https://forum.gamer.com.tw/B.php?bsn=19017",
      "category_slug": "pc",
      "category_label": "PC遊戲哈啦區"
    },
    {
      "rank": 15,
      "title": "Minecraft 我的世界（當個創世神）",
      "popularity": 21491,
      "article": 41,
      "bsn": 18673,
      "board_url": "https://forum.gamer.com.tw/B.php?bsn=18673",
      "category_slug": "pc",
      "category_label": "PC遊戲哈啦區"
    },
    {
      "rank": 16,
      "title": "WOW 魔獸世界",
      "popularity": 18132,
      "article": 8,
      "bsn": 5219,
      "board_url": "https://forum.gamer.com.tw/B.php?bsn=5219",
      "category_slug": "pc",
      "category_label": "PC遊戲哈啦區"
    },
    {
      "rank": 17,
      "title": "戰鎚：40K 系列（Warhammer:40000）",
      "popularity": 13011,
      "article": 5,
      "bsn": 7506,
      "board_url": "https://forum.gamer.com.tw/B.php?bsn=7506",
      "category_slug": "pc",
      "category_label": "PC遊戲哈啦區"
    },
    {
      "rank": 18,
      "title": "赤血沙漠",
      "popularity": 12588,
      "article": 6,
      "bsn": 37615,
      "board_url": "https://forum.gamer.com.tw/B.php?bsn=37615",
      "category_slug": "pc",
      "category_label": "PC遊戲哈啦區"
    },
    {
      "rank": 19,
      "title": "RO 仙境傳說 Online：樂園",
      "popularity": 10876,
      "article": 3,
      "bsn": 83142,
      "board_url": "https://forum.gamer.com.tw/B.php?bsn=83142",
      "category_slug": "pc",
      "category_label": "PC遊戲哈啦區"
    },
    {
      "rank": 20,
      "title": "羅馬拓荒錄",
      "popularity": 10526,
      "article": 6,
      "bsn": 85018,
      "board_url": "https://forum.gamer.com.tw/B.php?bsn=85018",
      "category_slug": "pc",
      "category_label": "PC遊戲哈啦區"
    },
    {
      "rank": 21,
      "title": "新瑪奇 Mabinogi",
      "popularity": 9969,
      "article": 1,
      "bsn": 7422,
      "board_url": "https://forum.gamer.com.tw/B.php?bsn=7422",
      "category_slug": "pc",
      "category_label": "PC遊戲哈啦區"
    },
    {
      "rank": 22,
      "title": "Garena 三角洲行動",
      "popularity": 8837,
      "article": 7,
      "bsn": 78342,
      "board_url": "https://forum.gamer.com.tw/B.php?bsn=78342",
      "category_slug": "pc",
      "category_label": "PC遊戲哈啦區"
    },
    {
      "rank": 23,
      "title": "Freestyle: Reboot",
      "popularity": 8107,
      "article": 8,
      "bsn": 85300,
      "board_url": "https://forum.gamer.com.tw/B.php?bsn=85300",
      "category_slug": "pc",
      "category_label": "PC遊戲哈啦區"
    },
    {
      "rank": 24,
      "title": "鬥陣特攻",
      "popularity": 7708,
      "article": 6,
      "bsn": 27362,
      "board_url": "https://forum.gamer.com.tw/B.php?bsn=27362",
      "category_slug": "pc",
      "category_label": "PC遊戲哈啦區"
    },
    {
      "rank": 25,
      "title": "APEX 英雄",
      "popularity": 7705,
      "article": 1,
      "bsn": 36072,
      "board_url": "https://forum.gamer.com.tw/B.php?bsn=36072",
      "category_slug": "pc",
      "category_label": "PC遊戲哈啦區"
    },
    {
      "rank": 26,
      "title": "雀魂麻將majsoul",
      "popularity": 7589,
      "article": 4,
      "bsn": 36476,
      "board_url": "https://forum.gamer.com.tw/B.php?bsn=36476",
      "category_slug": "pc",
      "category_label": "PC遊戲哈啦區"
    },
    {
      "rank": 27,
      "title": "天堂Lineage",
      "popularity": 7428,
      "article": 0,
      "bsn": 842,
      "board_url": "https://forum.gamer.com.tw/B.php?bsn=842",
      "category_slug": "pc",
      "category_label": "PC遊戲哈啦區"
    },
    {
      "rank": 28,
      "title": "Warframe",
      "popularity": 7121,
      "article": 10,
      "bsn": 22797,
      "board_url": "https://forum.gamer.com.tw/B.php?bsn=22797",
      "category_slug": "pc",
      "category_label": "PC遊戲哈啦區"
    },
    {
      "rank": 29,
      "title": "電馭叛客 2077",
      "popularity": 6983,
      "article": 1,
      "bsn": 23379,
      "board_url": "https://forum.gamer.com.tw/B.php?bsn=23379",
      "category_slug": "pc",
      "category_label": "PC遊戲哈啦區"
    },
    {
      "rank": 30,
      "title": "CS Online﹝絕對武力﹞",
      "popularity": 6584,
      "article": 1,
      "bsn": 11902,
      "board_url": "https://forum.gamer.com.tw/B.php?bsn=11902",
      "category_slug": "pc",
      "category_label": "PC遊戲哈啦區"
    },
    {
      "rank": 31,
      "title": "摩爾莊園",
      "popularity": 6503,
      "article": 0,
      "bsn": 16735,
      "board_url": "https://forum.gamer.com.tw/B.php?bsn=16735",
      "category_slug": "pc",
      "category_label": "PC遊戲哈啦區"
    },
    {
      "rank": 32,
      "title": "新衝天跑",
      "popularity": 5862,
      "article": 1,
      "bsn": 9426,
      "board_url": "https://forum.gamer.com.tw/B.php?bsn=9426",
      "category_slug": "pc",
      "category_label": "PC遊戲哈啦區"
    },
    {
      "rank": 33,
      "title": "新瑪奇英雄傳",
      "popularity": 5801,
      "article": 4,
      "bsn": 16583,
      "board_url": "https://forum.gamer.com.tw/B.php?bsn=16583",
      "category_slug": "pc",
      "category_label": "PC遊戲哈啦區"
    },
    {
      "rank": 34,
      "title": "希望戀曲 Online",
      "popularity": 5772,
      "article": 0,
      "bsn": 18041,
      "board_url": "https://forum.gamer.com.tw/B.php?bsn=18041",
      "category_slug": "pc",
      "category_label": "PC遊戲哈啦區"
    },
    {
      "rank": 35,
      "title": "柏德之門 系列",
      "popularity": 5723,
      "article": 0,
      "bsn": 2954,
      "board_url": "https://forum.gamer.com.tw/B.php?bsn=2954",
      "category_slug": "pc",
      "category_label": "PC遊戲哈啦區"
    },
    {
      "rank": 36,
      "title": "活俠傳",
      "popularity": 5571,
      "article": 1,
      "bsn": 73317,
      "board_url": "https://forum.gamer.com.tw/B.php?bsn=73317",
      "category_slug": "pc",
      "category_label": "PC遊戲哈啦區"
    },
    {
      "rank": 37,
      "title": "幻獸帕魯",
      "popularity": 5555,
      "article": 0,
      "bsn": 71458,
      "board_url": "https://forum.gamer.com.tw/B.php?bsn=71458",
      "category_slug": "pc",
      "category_label": "PC遊戲哈啦區"
    },
    {
      "rank": 38,
      "title": "天國降臨：救贖 系列",
      "popularity": 5250,
      "article": 0,
      "bsn": 30945,
      "board_url": "https://forum.gamer.com.tw/B.php?bsn=30945",
      "category_slug": "pc",
      "category_label": "PC遊戲哈啦區"
    },
    {
      "rank": 39,
      "title": "龍胤立志傳",
      "popularity": 5201,
      "article": 0,
      "bsn": 84973,
      "board_url": "https://forum.gamer.com.tw/B.php?bsn=84973",
      "category_slug": "pc",
      "category_label": "PC遊戲哈啦區"
    },
    {
      "rank": 40,
      "title": "Once Human",
      "popularity": 5111,
      "article": 2,
      "bsn": 78260,
      "board_url": "https://forum.gamer.com.tw/B.php?bsn=78260",
      "category_slug": "pc",
      "category_label": "PC遊戲哈啦區"
    },
    {
      "rank": 41,
      "title": "戰艦世界 World of Warships",
      "popularity": 4486,
      "article": 0,
      "bsn": 21052,
      "board_url": "https://forum.gamer.com.tw/B.php?bsn=21052",
      "category_slug": "pc",
      "category_label": "PC遊戲哈啦區"
    },
    {
      "rank": 42,
      "title": "飄流幻境 Online",
      "popularity": 4162,
      "article": 0,
      "bsn": 8897,
      "board_url": "https://forum.gamer.com.tw/B.php?bsn=8897",
      "category_slug": "pc",
      "category_label": "PC遊戲哈啦區"
    },
    {
      "rank": 43,
      "title": "大俠立志傳",
      "popularity": 4148,
      "article": 0,
      "bsn": 76900,
      "board_url": "https://forum.gamer.com.tw/B.php?bsn=76900",
      "category_slug": "pc",
      "category_label": "PC遊戲哈啦區"
    },
    {
      "rank": 44,
      "title": "魔力寶貝",
      "popularity": 4057,
      "article": 0,
      "bsn": 2577,
      "board_url": "https://forum.gamer.com.tw/B.php?bsn=2577",
      "category_slug": "pc",
      "category_label": "PC遊戲哈啦區"
    },
    {
      "rank": 45,
      "title": "上古卷軸 系列(The Elder Scrolls)",
      "popularity": 4005,
      "article": 1,
      "bsn": 2526,
      "board_url": "https://forum.gamer.com.tw/B.php?bsn=2526",
      "category_slug": "pc",
      "category_label": "PC遊戲哈啦區"
    },
    {
      "rank": 46,
      "title": "戰車世界 World of Tanks",
      "popularity": 4002,
      "article": 3,
      "bsn": 18214,
      "board_url": "https://forum.gamer.com.tw/B.php?bsn=18214",
      "category_slug": "pc",
      "category_label": "PC遊戲哈啦區"
    },
    {
      "rank": 47,
      "title": "巫師 The Witcher 系列",
      "popularity": 3886,
      "article": 0,
      "bsn": 7364,
      "board_url": "https://forum.gamer.com.tw/B.php?bsn=7364",
      "category_slug": "pc",
      "category_label": "PC遊戲哈啦區"
    },
    {
      "rank": 48,
      "title": "巨商",
      "popularity": 3797,
      "article": 0,
      "bsn": 5079,
      "board_url": "https://forum.gamer.com.tw/B.php?bsn=5079",
      "category_slug": "pc",
      "category_label": "PC遊戲哈啦區"
    },
    {
      "rank": 49,
      "title": "Dead by Daylight（黎明死線）",
      "popularity": 3734,
      "article": 3,
      "bsn": 29919,
      "board_url": "https://forum.gamer.com.tw/B.php?bsn=29919",
      "category_slug": "pc",
      "category_label": "PC遊戲哈啦區"
    },
    {
      "rank": 50,
      "title": "艦隊 Collection",
      "popularity": 3584,
      "article": 0,
      "bsn": 24698,
      "board_url": "https://forum.gamer.com.tw/B.php?bsn=24698",
      "category_slug": "pc",
      "category_label": "PC遊戲哈啦區"
    },
    {
      "rank": 51,
      "title": "魔獸爭霸",
      "popularity": 3493,
      "article": 1,
      "bsn": 3044,
      "board_url": "https://forum.gamer.com.tw/B.php?bsn=3044",
      "category_slug": "pc",
      "category_label": "PC遊戲哈啦區"
    },
    {
      "rank": 52,
      "title": "世紀帝國 系列",
      "popularity": 3454,
      "article": 1,
      "bsn": 1122,
      "board_url": "https://forum.gamer.com.tw/B.php?bsn=1122",
      "category_slug": "pc",
      "category_label": "PC遊戲哈啦區"
    },
    {
      "rank": 53,
      "title": "賽爾號",
      "popularity": 3311,
      "article": 0,
      "bsn": 18072,
      "board_url": "https://forum.gamer.com.tw/B.php?bsn=18072",
      "category_slug": "pc",
      "category_label": "PC遊戲哈啦區"
    },
    {
      "rank": 54,
      "title": "Slay the Spire",
      "popularity": 3119,
      "article": 2,
      "bsn": 33661,
      "board_url": "https://forum.gamer.com.tw/B.php?bsn=33661",
      "category_slug": "pc",
      "category_label": "PC遊戲哈啦區"
    },
    {
      "rank": 55,
      "title": "潛水員戴夫",
      "popularity": 3060,
      "article": 0,
      "bsn": 35628,
      "board_url": "https://forum.gamer.com.tw/B.php?bsn=35628",
      "category_slug": "pc",
      "category_label": "PC遊戲哈啦區"
    },
    {
      "rank": 56,
      "title": "戰意",
      "popularity": 3045,
      "article": 2,
      "bsn": 30786,
      "board_url": "https://forum.gamer.com.tw/B.php?bsn=30786",
      "category_slug": "pc",
      "category_label": "PC遊戲哈啦區"
    },
    {
      "rank": 57,
      "title": "異塵餘生 系列",
      "popularity": 3040,
      "article": 0,
      "bsn": 2023,
      "board_url": "https://forum.gamer.com.tw/B.php?bsn=2023",
      "category_slug": "pc",
      "category_label": "PC遊戲哈啦區"
    },
    {
      "rank": 58,
      "title": "艾爾之光",
      "popularity": 2988,
      "article": 0,
      "bsn": 12259,
      "board_url": "https://forum.gamer.com.tw/B.php?bsn=12259",
      "category_slug": "pc",
      "category_label": "PC遊戲哈啦區"
    },
    {
      "rank": 59,
      "title": "戰地風雲",
      "popularity": 2972,
      "article": 0,
      "bsn": 4220,
      "board_url": "https://forum.gamer.com.tw/B.php?bsn=4220",
      "category_slug": "pc",
      "category_label": "PC遊戲哈啦區"
    },
    {
      "rank": 60,
      "title": "天外Online",
      "popularity": 2927,
      "article": 0,
      "bsn": 6784,
      "board_url": "https://forum.gamer.com.tw/B.php?bsn=6784",
      "category_slug": "pc",
      "category_label": "PC遊戲哈啦區"
    },
    {
      "rank": 61,
      "title": "千年戰爭 Aigis～一般版～",
      "popularity": 2912,
      "article": 0,
      "bsn": 27417,
      "board_url": "https://forum.gamer.com.tw/B.php?bsn=27417",
      "category_slug": "pc",
      "category_label": "PC遊戲哈啦區"
    },
    {
      "rank": 62,
      "title": "空洞騎士  系列",
      "popularity": 2901,
      "article": 1,
      "bsn": 27487,
      "board_url": "https://forum.gamer.com.tw/B.php?bsn=27487",
      "category_slug": "pc",
      "category_label": "PC遊戲哈啦區"
    },
    {
      "rank": 63,
      "title": "爐石戰記",
      "popularity": 2827,
      "article": 1,
      "bsn": 24044,
      "board_url": "https://forum.gamer.com.tw/B.php?bsn=24044",
      "category_slug": "pc",
      "category_label": "PC遊戲哈啦區"
    },
    {
      "rank": 64,
      "title": "Core Keeper",
      "popularity": 2772,
      "article": 1,
      "bsn": 74451,
      "board_url": "https://forum.gamer.com.tw/B.php?bsn=74451",
      "category_slug": "pc",
      "category_label": "PC遊戲哈啦區"
    },
    {
      "rank": 65,
      "title": "九日",
      "popularity": 2742,
      "article": 3,
      "bsn": 74687,
      "board_url": "https://forum.gamer.com.tw/B.php?bsn=74687",
      "category_slug": "pc",
      "category_label": "PC遊戲哈啦區"
    },
    {
      "rank": 66,
      "title": "決勝時刻",
      "popularity": 2701,
      "article": 2,
      "bsn": 5371,
      "board_url": "https://forum.gamer.com.tw/B.php?bsn=5371",
      "category_slug": "pc",
      "category_label": "PC遊戲哈啦區"
    },
    {
      "rank": 67,
      "title": "三國志 系列",
      "popularity": 2692,
      "article": 0,
      "bsn": 6331,
      "board_url": "https://forum.gamer.com.tw/B.php?bsn=6331",
      "category_slug": "pc",
      "category_label": "PC遊戲哈啦區"
    },
    {
      "rank": 68,
      "title": "戰慄時空之絕對武力( CS )",
      "popularity": 2677,
      "article": 0,
      "bsn": 1473,
      "board_url": "https://forum.gamer.com.tw/B.php?bsn=1473",
      "category_slug": "pc",
      "category_label": "PC遊戲哈啦區"
    },
    {
      "rank": 69,
      "title": "暗黑破壞神 3",
      "popularity": 2577,
      "article": 0,
      "bsn": 21400,
      "board_url": "https://forum.gamer.com.tw/B.php?bsn=21400",
      "category_slug": "pc",
      "category_label": "PC遊戲哈啦區"
    },
    {
      "rank": 70,
      "title": "Grim Dawn",
      "popularity": 2547,
      "article": 2,
      "bsn": 19441,
      "board_url": "https://forum.gamer.com.tw/B.php?bsn=19441",
      "category_slug": "pc",
      "category_label": "PC遊戲哈啦區"
    },
    {
      "rank": 71,
      "title": "第一繼承者",
      "popularity": 2504,
      "article": 2,
      "bsn": 71782,
      "board_url": "https://forum.gamer.com.tw/B.php?bsn=71782",
      "category_slug": "pc",
      "category_label": "PC遊戲哈啦區"
    },
    {
      "rank": 72,
      "title": "特戰英豪",
      "popularity": 2469,
      "article": 0,
      "bsn": 38093,
      "board_url": "https://forum.gamer.com.tw/B.php?bsn=38093",
      "category_slug": "pc",
      "category_label": "PC遊戲哈啦區"
    },
    {
      "rank": 73,
      "title": "黑神話 系列",
      "popularity": 2446,
      "article": 1,
      "bsn": 39114,
      "board_url": "https://forum.gamer.com.tw/B.php?bsn=39114",
      "category_slug": "pc",
      "category_label": "PC遊戲哈啦區"
    },
    {
      "rank": 74,
      "title": "方舟 系列",
      "popularity": 2441,
      "article": 0,
      "bsn": 28423,
      "board_url": "https://forum.gamer.com.tw/B.php?bsn=28423",
      "category_slug": "pc",
      "category_label": "PC遊戲哈啦區"
    },
    {
      "rank": 75,
      "title": "背包夥伴",
      "popularity": 2409,
      "article": 23,
      "bsn": 85261,
      "board_url": "https://forum.gamer.com.tw/B.php?bsn=85261",
      "category_slug": "pc",
      "category_label": "PC遊戲哈啦區"
    },
    {
      "rank": 76,
      "title": "絕地求生 PUBG",
      "popularity": 2380,
      "article": 3,
      "bsn": 30630,
      "board_url": "https://forum.gamer.com.tw/B.php?bsn=30630",
      "category_slug": "pc",
      "category_label": "PC遊戲哈啦區"
    },
    {
      "rank": 77,
      "title": "戰爭雷霆（War Thunder）",
      "popularity": 2275,
      "article": 1,
      "bsn": 20947,
      "board_url": "https://forum.gamer.com.tw/B.php?bsn=20947",
      "category_slug": "pc",
      "category_label": "PC遊戲哈啦區"
    },
    {
      "rank": 78,
      "title": "Subnautica",
      "popularity": 2217,
      "article": 0,
      "bsn": 26553,
      "board_url": "https://forum.gamer.com.tw/B.php?bsn=26553",
      "category_slug": "pc",
      "category_label": "PC遊戲哈啦區"
    },
    {
      "rank": 79,
      "title": "火炬之光：無限",
      "popularity": 2214,
      "article": 0,
      "bsn": 74756,
      "board_url": "https://forum.gamer.com.tw/B.php?bsn=74756",
      "category_slug": "pc",
      "category_label": "PC遊戲哈啦區"
    },
    {
      "rank": 80,
      "title": "星露谷物語 Stardew Valley",
      "popularity": 2205,
      "article": 0,
      "bsn": 20774,
      "board_url": "https://forum.gamer.com.tw/B.php?bsn=20774",
      "category_slug": "pc",
      "category_label": "PC遊戲哈啦區"
    },
    {
      "rank": 81,
      "title": "阿爾比恩 Online",
      "popularity": 2178,
      "article": 3,
      "bsn": 27044,
      "board_url": "https://forum.gamer.com.tw/B.php?bsn=27044",
      "category_slug": "pc",
      "category_label": "PC遊戲哈啦區"
    },
    {
      "rank": 82,
      "title": "霧鎖王國",
      "popularity": 2128,
      "article": 1,
      "bsn": 77537,
      "board_url": "https://forum.gamer.com.tw/B.php?bsn=77537",
      "category_slug": "pc",
      "category_label": "PC遊戲哈啦區"
    },
    {
      "rank": 83,
      "title": "劍靈 Blade & Soul",
      "popularity": 2107,
      "article": 7,
      "bsn": 12980,
      "board_url": "https://forum.gamer.com.tw/B.php?bsn=12980",
      "category_slug": "pc",
      "category_label": "PC遊戲哈啦區"
    },
    {
      "rank": 84,
      "title": "RPG製作大師",
      "popularity": 2098,
      "article": 0,
      "bsn": 4918,
      "board_url": "https://forum.gamer.com.tw/B.php?bsn=4918",
      "category_slug": "pc",
      "category_label": "PC遊戲哈啦區"
    },
    {
      "rank": 85,
      "title": "逸劍風雲決",
      "popularity": 2089,
      "article": 0,
      "bsn": 76881,
      "board_url": "https://forum.gamer.com.tw/B.php?bsn=76881",
      "category_slug": "pc",
      "category_label": "PC遊戲哈啦區"
    },
    {
      "rank": 86,
      "title": "仙劍奇俠傳 系列",
      "popularity": 2050,
      "article": 0,
      "bsn": 2417,
      "board_url": "https://forum.gamer.com.tw/B.php?bsn=2417",
      "category_slug": "pc",
      "category_label": "PC遊戲哈啦區"
    },
    {
      "rank": 87,
      "title": "逃離塔科夫",
      "popularity": 2037,
      "article": 1,
      "bsn": 29943,
      "board_url": "https://forum.gamer.com.tw/B.php?bsn=29943",
      "category_slug": "pc",
      "category_label": "PC遊戲哈啦區"
    },
    {
      "rank": 88,
      "title": "金庸群俠傳",
      "popularity": 1987,
      "article": 0,
      "bsn": 10859,
      "board_url": "https://forum.gamer.com.tw/B.php?bsn=10859",
      "category_slug": "pc",
      "category_label": "PC遊戲哈啦區"
    },
    {
      "rank": 89,
      "title": "武林同萌傳Online",
      "popularity": 1975,
      "article": 0,
      "bsn": 6960,
      "board_url": "https://forum.gamer.com.tw/B.php?bsn=6960",
      "category_slug": "pc",
      "category_label": "PC遊戲哈啦區"
    },
    {
      "rank": 90,
      "title": "吸血鬼倖存者",
      "popularity": 1963,
      "article": 0,
      "bsn": 74171,
      "board_url": "https://forum.gamer.com.tw/B.php?bsn=74171",
      "category_slug": "pc",
      "category_label": "PC遊戲哈啦區"
    },
    {
      "rank": 91,
      "title": "R.E.P.O.",
      "popularity": 1944,
      "article": 0,
      "bsn": 82396,
      "board_url": "https://forum.gamer.com.tw/B.php?bsn=82396",
      "category_slug": "pc",
      "category_label": "PC遊戲哈啦區"
    },
    {
      "rank": 92,
      "title": "Stoneshard",
      "popularity": 1940,
      "article": 0,
      "bsn": 38794,
      "board_url": "https://forum.gamer.com.tw/B.php?bsn=38794",
      "category_slug": "pc",
      "category_label": "PC遊戲哈啦區"
    },
    {
      "rank": 93,
      "title": "黑帝斯",
      "popularity": 1911,
      "article": 0,
      "bsn": 35739,
      "board_url": "https://forum.gamer.com.tw/B.php?bsn=35739",
      "category_slug": "pc",
      "category_label": "PC遊戲哈啦區"
    },
    {
      "rank": 94,
      "title": "鬼谷八荒",
      "popularity": 1885,
      "article": 0,
      "bsn": 70540,
      "board_url": "https://forum.gamer.com.tw/B.php?bsn=70540",
      "category_slug": "pc",
      "category_label": "PC遊戲哈啦區"
    },
    {
      "rank": 95,
      "title": "失落的方舟（Lost Ark）",
      "popularity": 1873,
      "article": 0,
      "bsn": 27410,
      "board_url": "https://forum.gamer.com.tw/B.php?bsn=27410",
      "category_slug": "pc",
      "category_label": "PC遊戲哈啦區"
    },
    {
      "rank": 96,
      "title": "魔獸世界：經典版",
      "popularity": 1868,
      "article": 1,
      "bsn": 36703,
      "board_url": "https://forum.gamer.com.tw/B.php?bsn=36703",
      "category_slug": "pc",
      "category_label": "PC遊戲哈啦區"
    },
    {
      "rank": 97,
      "title": "殭屍毀滅工程 Project Zomboid",
      "popularity": 1842,
      "article": 0,
      "bsn": 20202,
      "board_url": "https://forum.gamer.com.tw/B.php?bsn=20202",
      "category_slug": "pc",
      "category_label": "PC遊戲哈啦區"
    },
    {
      "rank": 98,
      "title": "幕府將軍、全軍破敵系列",
      "popularity": 1831,
      "article": 0,
      "bsn": 4236,
      "board_url": "https://forum.gamer.com.tw/B.php?bsn=4236",
      "category_slug": "pc",
      "category_label": "PC遊戲哈啦區"
    },
    {
      "rank": 99,
      "title": "靈魂面甲",
      "popularity": 1793,
      "article": 1,
      "bsn": 79921,
      "board_url": "https://forum.gamer.com.tw/B.php?bsn=79921",
      "category_slug": "pc",
      "category_label": "PC遊戲哈啦區"
    },
    {
      "rank": 100,
      "title": "邊緣世界",
      "popularity": 1790,
      "article": 0,
      "bsn": 27313,
      "board_url": "https://forum.gamer.com.tw/B.php?bsn=27313",
      "category_slug": "pc",
      "category_label": "PC遊戲哈啦區"
    },
    {
      "rank": 101,
      "title": "歐洲美洲卡車模擬 系列",
      "popularity": 1790,
      "article": 0,
      "bsn": 16179,
      "board_url": "https://forum.gamer.com.tw/B.php?bsn=16179",
      "category_slug": "pc",
      "category_label": "PC遊戲哈啦區"
    },
    {
      "rank": 102,
      "title": "永恆輪迴",
      "popularity": 1619,
      "article": 0,
      "bsn": 38217,
      "board_url": "https://forum.gamer.com.tw/B.php?bsn=38217",
      "category_slug": "pc",
      "category_label": "PC遊戲哈啦區"
    },
    {
      "rank": 103,
      "title": "漫威爭鋒",
      "popularity": 1603,
      "article": 1,
      "bsn": 79940,
      "board_url": "https://forum.gamer.com.tw/B.php?bsn=79940",
      "category_slug": "pc",
      "category_label": "PC遊戲哈啦區"
    },
    {
      "rank": 104,
      "title": "亂 2 Online",
      "popularity": 1577,
      "article": 0,
      "bsn": 5270,
      "board_url": "https://forum.gamer.com.tw/B.php?bsn=5270",
      "category_slug": "pc",
      "category_label": "PC遊戲哈啦區"
    },
    {
      "rank": 105,
      "title": "童話 Online",
      "popularity": 1492,
      "article": 0,
      "bsn": 4211,
      "board_url": "https://forum.gamer.com.tw/B.php?bsn=4211",
      "category_slug": "pc",
      "category_label": "PC遊戲哈啦區"
    },
    {
      "rank": 106,
      "title": "對魔忍 RPG",
      "popularity": 1488,
      "article": 1,
      "bsn": 35303,
      "board_url": "https://forum.gamer.com.tw/B.php?bsn=35303",
      "category_slug": "pc",
      "category_label": "PC遊戲哈啦區"
    },
    {
      "rank": 107,
      "title": "俠客風雲傳 系列",
      "popularity": 1424,
      "article": 0,
      "bsn": 3148,
      "board_url": "https://forum.gamer.com.tw/B.php?bsn=3148",
      "category_slug": "pc",
      "category_label": "PC遊戲哈啦區"
    },
    {
      "rank": 108,
      "title": "明星志願 系列",
      "popularity": 1407,
      "article": 0,
      "bsn": 866,
      "board_url": "https://forum.gamer.com.tw/B.php?bsn=866",
      "category_slug": "pc",
      "category_label": "PC遊戲哈啦區"
    },
    {
      "rank": 109,
      "title": "逃離鴨科夫",
      "popularity": 1400,
      "article": 0,
      "bsn": 83580,
      "board_url": "https://forum.gamer.com.tw/B.php?bsn=83580",
      "category_slug": "pc",
      "category_label": "PC遊戲哈啦區"
    },
    {
      "rank": 110,
      "title": "騎馬與砍殺",
      "popularity": 1369,
      "article": 2,
      "bsn": 16393,
      "board_url": "https://forum.gamer.com.tw/B.php?bsn=16393",
      "category_slug": "pc",
      "category_label": "PC遊戲哈啦區"
    },
    {
      "rank": 111,
      "title": "永恆冒險 Grand Chase Classic",
      "popularity": 1364,
      "article": 0,
      "bsn": 8948,
      "board_url": "https://forum.gamer.com.tw/B.php?bsn=8948",
      "category_slug": "pc",
      "category_label": "PC遊戲哈啦區"
    },
    {
      "rank": 112,
      "title": "星海爭霸",
      "popularity": 1356,
      "article": 1,
      "bsn": 3037,
      "board_url": "https://forum.gamer.com.tw/B.php?bsn=3037",
      "category_slug": "pc",
      "category_label": "PC遊戲哈啦區"
    },
    {
      "rank": 113,
      "title": "魔力寶貝：永恆初心",
      "popularity": 1338,
      "article": 1,
      "bsn": 70151,
      "board_url": "https://forum.gamer.com.tw/B.php?bsn=70151",
      "category_slug": "pc",
      "category_label": "PC遊戲哈啦區"
    },
    {
      "rank": 114,
      "title": "新熱血江湖 Online",
      "popularity": 1338,
      "article": 0,
      "bsn": 8294,
      "board_url": "https://forum.gamer.com.tw/B.php?bsn=8294",
      "category_slug": "pc",
      "category_label": "PC遊戲哈啦區"
    },
    {
      "rank": 115,
      "title": "A.V.A 戰地之王",
      "popularity": 1300,
      "article": 1,
      "bsn": 16618,
      "board_url": "https://forum.gamer.com.tw/B.php?bsn=16618",
      "category_slug": "pc",
      "category_label": "PC遊戲哈啦區"
    },
    {
      "rank": 116,
      "title": "石器時代 系列",
      "popularity": 1289,
      "article": 1,
      "bsn": 1571,
      "board_url": "https://forum.gamer.com.tw/B.php?bsn=1571",
      "category_slug": "pc",
      "category_label": "PC遊戲哈啦區"
    },
    {
      "rank": 117,
      "title": "新墨魂 Online",
      "popularity": 1234,
      "article": 2,
      "bsn": 38561,
      "board_url": "https://forum.gamer.com.tw/B.php?bsn=38561",
      "category_slug": "pc",
      "category_label": "PC遊戲哈啦區"
    },
    {
      "rank": 118,
      "title": "激戰 2（Guild Wars 2 ）",
      "popularity": 1218,
      "article": 1,
      "bsn": 16901,
      "board_url": "https://forum.gamer.com.tw/B.php?bsn=16901",
      "category_slug": "pc",
      "category_label": "PC遊戲哈啦區"
    },
    {
      "rank": 119,
      "title": "東方Project 系列",
      "popularity": 1208,
      "article": 7,
      "bsn": 10039,
      "board_url": "https://forum.gamer.com.tw/B.php?bsn=10039",
      "category_slug": "pc",
      "category_label": "PC遊戲哈啦區"
    },
    {
      "rank": 120,
      "title": "遙遙西土",
      "popularity": 1196,
      "article": 0,
      "bsn": 82985,
      "board_url": "https://forum.gamer.com.tw/B.php?bsn=82985",
      "category_slug": "pc",
      "category_label": "PC遊戲哈啦區"
    }
  ]
}
